Workbook

Sheet Summary
D1: RawData | E1: Distinct | F1: Duplicates
B2: Total Rows | D2: =ROWS(RawData!A2:A4130) -> 4129 | E2: =ROWS(Distinct!A2:A3528) -> 3527 | F2: =ROWS(Duplicates!A2:A1131) -> 1130
B3: Row Counts(with Score) | D3: =COUNTIF(RawData!E2:E4130,"<>") -> 3985 | E3: =COUNTIF(Distinct!E2:E4130,"<>") -> 3399 | F3: =COUNTIF(Duplicates!E2:E4130,"<>") -> 1103
B5: Data Types:
B6: Submission ID | D6: String
B7: Respondent ID | D7: String
B8: Submitted at | D8: Date
B9: Loan Id | D9: String
B10: Using a scale from 0 (not likely) to 10 (very likely), how likely are you to recommend ABC Phones to friends or family? | D10: Integer
B11: What is the main reason for your score? | D11: String
B12: What is one thing we could do to improve your experience with us? | D12: String
B13: Are you happy with the quality and performance of your device? | D13: String
B14: Are you happy with the service and support provided by ABC Phones? | D14: String

Sheet RawData
A1: Submission ID | B1: Respondent ID | C1: Submitted at | D1: Loan Id | E1: Using a scale from 0 (not likely) to 10 (very likely), how likely are you to recommend ABC Phones to friends or family? | F1: What is the main reason for your score? | G1: What is one thing we could do to improve your experience with us? | H1: Are you happy with the quality and performance of your device? | I1: Are you happy with the service and support provided by ABC Phones? | J1: Have you ever experienced a delay in your payment reflecting in your ABC account? | K1: Have you ever had difficulty getting assistance from ABC Phones customer support when needed? | L1: (If Yes) – Please describe the challenge you faced and how we can improve your experience. | M1: Have you experienced any battery-related issues with your MoPhones device? | N1: Have you used the MoPhones app (MoApp) to manage your account or make payments? | O1: Which communication channel do you prefer when contacting MoPhones for inquiries or support? | P1: Have you ever had your phone lock despite making a payment on time? | Q1: Any other Feedback?
A2: BzK4Q11 | B2: k4z1Y6 | C2: 45769.635 | D2: rec2FCxHhqXw6aKRU | E2: 6 | H2: Yes | I2: Yes | J2: Yes | K2: Yes | L2: Unlocking my phone | M2: No | N2: Yes, and I am satisfied with the MoApp | O2: MoPhones App | P2: Yes | Q2: N/A
A3: b59V45Z | B3: AY9GMk | C3: 45769.637 | D3: recQcLWbPcep18Wdw | E3: 10 | H3: Yes | I3: Yes | J3: No | K3: No | L3: Response team always on time | M3: No | N3: Yes, and I am satisfied with the MoApp | O3: Free SMS – 25044 | P3: No | Q3: Would like to upgrade once I'm done with this loan
A4: GxKvYKO | B4: eGz8Ek | C4: 45769.647 | D4: recei9UEU0e5F9HuG | E4: 5 | H4: No | I4: No | J4: No | K4: Yes | L4: I bought a Samsung A42 which has fingerprint lock that doesn't work since I bought it from ABC, I took it back and it's wasn't fixed.. Then the Phone has an on and Off network issues | M4: No | N4: Yes, and I am satisfied with the MoApp | O4: Phone Call – +254 728 444 442 or +254 709 924 404 | P4: Yes | Q4: Good service and efficient response
A5: A7KP49z | B5: LjOx7j | C5: 45769.653 | D5: recosDWAJvWzAKgLv | E5: 1 | H5: No | I5: No | J5: Yes | K5: Yes | L5: Delays | M5: Yes | N5: Yes, but I am not satisfied with the MoApp
A6: 81zo6pr | B6: 7YE0RR | C6: 45769.653 | D6: recTJng0Mj0dJP1kv | E6: 1 | H6: No | I6: No | J6: Yes | K6: Yes | L6: Not satisfied with my phone | M6: Yes | N6: Yes, but I am not satisfied with the MoApp | O6: MoPhones App | P6: Yes | Q6: Not satisfied with my phone
A7: xXjxR5J | B7: RQjeLp | C7: 45769.653 | D7: recPKFOtpkS0z9Kpp | E7: 10 | H7: Yes | I7: Yes | J7: No | K7: No | L7: . | M7: No | N7: Yes, and I am satisfied with the MoApp | O7: Phone Call – +254 728 444 442 or +254 709 924 404 | P7: No | Q7: .
A8: GxKvQ6L | B8: ljz2Mo | C8: 45769.653 | D8: rechy4Nf0Ihxrdy85 | E8: 10
A9: rjBykB2 | B9: k4zjvo | C9: 45769.654 | D9: recayIesPKGAMilkX | E9: 0
A10: 5B4KeaM | B10: k4zjZJ | C10: 45769.654 | D10: rec86PnPzgTEunR4Q | E10: 9 | H10: No | I10: No | J10: Yes | K10: Yes | L10: There is a lot to be | M10: No | N10: Yes, and I am satisfied with the MoApp | O10: MoPhones App | P10: Yes | Q10: None
A11: 5B4Kp16 | B11: rQY9pN | C11: 45769.656 | D11: recJKsUBTzHl4IGK3 | E11: 10 | H11: Yes | I11: Yes | J11: Yes | K11: No, I have never looked for customer care | L11: N/A | M11: No | N11: Yes, and I am satisfied with the MoApp | O11: Phone Call – +254 728 444 442 or +254 709 924 404 | P11: No | Q11: N/A
A12: eqDZYBO | B12: AY9RGD | C12: 45769.656 | D12: recUmt3DbYL0gb025 | E12: 10 | H12: Yes | I12: Yes | J12: No | K12: No | L12: None | M12: No | N12: Yes, and I am satisfied with the MoApp | O12: Reach Out via a Sales Agent | P12: No | Q12: None
A13: aQeNaYv | B13: yRD5Dg | C13: 45769.656 | D13: recVOllpG6mFoGtaV | E13: 8 | H13: No | I13: Yes | J13: No | K13: No | L13: Battery can't store charge I need a replaced of battery | M13: Yes | N13: Yes, and I am satisfied with the MoApp | O13: Phone Call – +254 728 444 442 or +254 709 924 404 | P13: No | Q13: Kindly exchange my battery
A14: dWNqK2d | B14: gVzV5M | C14: 45769.656 | D14: reciMIpVjO2lBzHt8 | E14: 7 | H14: Yes | I14: Yes | J14: Yes | K14: No | L14: Payment terms are harsh | M14: No | N14: No, I have never used it | O14: Phone Call – +254 728 444 442 or +254 709 924 404 | P14: Yes | Q14: You need to check on payment terms
A15: WOr9jYJ | B15: AY9RN0 | C15: 45769.656 | D15: receJwqtM49LS8gE8 | E15: 10 | H15: Yes | I15: Yes | J15: Yes | K15: No, I have never looked for customer care | L15: No | M15: No | N15: No, I have never used it | O15: Phone Call – +254 728 444 442 or +254 709 924 404 | P15: Yes | Q15: Am happy for your service
A16: zxNX1Q8 | B16: 4YO00O | C16: 45769.656 | D16: recB2N3ejw9jeBo4l | E16: 0 | H16: No | I16: No | J16: Yes | K16: Yes | L16: My phone is not working despite payment | M16: Yes | N16: Yes, and I am satisfied with the MoApp | O16: Phone Call – +254 728 444 442 or +254 709 924 404 | P16: Yes | Q16: My phone has a charging problem since
A17: jabDkpQ | B17: gVzPBK | C17: 45769.657 | D17: recK9QseqaimraXBE | E17: 8 | H17: Yes | I17: Yes | J17: Yes | K17: No | L17: Have a 24/7 customer care services | M17: Yes | N17: Yes, but I am not satisfied with the MoApp | O17: Phone Call – +254 728 444 442 or +254 709 924 404 | P17: No | Q17: No
A18: PdDjkDx | B18: gVz85l | C18: 45769.658 | D18: rectavMBbkg1rwXIl | E18: 10 | H18: Yes | I18: Yes | J18: No | K18: No
A19: MeDK74X | B19: 8YrbNl | C19: 45769.659 | D19: recu8gML0JT6Cd9ES | E19: 3 | H19: No | I19: No | J19: Yes | K19: Yes | M19: Yes | N19: Yes, but I am not satisfied with the MoApp | O19: MoPhones App | P19: No | Q19: Improve in your app
A20: vGrjKyl | B20: 4YOlvb | C20: 45769.659 | D20: recHDnVDRlfvts5dQ | E20: 6 | H20: Yes | I20: Yes | J20: No | K20: Yes | L20: MOPHONES | M20: Yes | N20: Yes, and I am satisfied with the MoApp | O20: Free SMS – 25044 | P20: No | Q20: Nome
A21: XxrlzDL | B21: Qq4NYg | C21: 45769.66 | D21: recvDdpWZLA2VCChR | E21: 10 | H21: Yes | I21: No | J21: No | K21: Yes | L21: Support center should work 24\7 | M21: No | N21: No, I have never used it | O21: Phone Call – +254 728 444 442 or +254 709 924 404 | P21: Yes | Q21: No
A22: zxNXL0q | B22: AY9M4N | C22: 45769.66 | D22: rec7AnOdegQgCwyT6 | E22: 8 | H22: Yes | I22: Yes | J22: Yes | K22: No | L22: Avoid delay while approving a grace period | M22: Yes | N22: Yes, and I am satisfied with the MoApp | O22: Free SMS – 25044 | P22: Yes | Q22: None
A23: Y5RDkx6 | B23: k4z8rZ | C23: 45769.66 | D23: recIZZtnG0LN1MpqF | E23: 9 | H23: Yes | I23: Yes | J23: Yes | K23: Yes | L23: You don't accept calls
A24: 7RblMyZ | B24: ljz8GB | C24: 45769.66 | D24: recAyJ8v8VJuecwtB | E24: 9 | H24: Yes | I24: Yes | J24: No | K24: No
A25: kd9av2R | B25: OZEx27 | C25: 45769.661 | D25: recjPY1G5I3fQxMOn | E25: 8 | H25: Yes | I25: Yes | J25: No | K25: No | L25: Non | M25: No | N25: Yes, but I am not satisfied with the MoApp | O25: Free SMS – 25044 | P25: No | Q25: No
A26: 2EB87Zg | B26: dozJVr | C26: 45769.662 | D26: rec4fZqbuemGwnwZF | E26: 10 | H26: Yes | I26: Yes | J26: No | K26: No | L26: No | M26: Yes | N26: No, I have never used it | O26: Phone Call – +254 728 444 442 or +254 709 924 404 | P26: No | Q26: No
A27: MeDKVb8 | B27: Jrovpz | C27: 45769.662 | D27: recl4egRn2rQH4mO0 | H27: Yes | I27: Yes
A28: Y5RD9G0 | B28: Jrov97 | C28: 45769.662 | D28: recQJWCGAZ7yuy0k7 | E28: 8 | H28: Yes | I28: Yes | J28: Yes | K28: No | L28: No
A29: 9qXG4Z4 | B29: GVbAez | C29: 45769.662 | D29: rec6r5JWy61FR24fB | E29: 9 | H29: Yes | I29: Yes | J29: No | K29: No
A30: xXjxvbv | B30: RQjqej | C30: 45769.662 | D30: recEx6e0qdGKb242p | E30: 10 | H30: Yes | I30: Yes | J30: No | K30: No | L30: No | M30: Yes | N30: Yes, and I am satisfied with the MoApp | O30: MoPhones App | P30: No | Q30: Had some challenges at the beginning but they were sorted.The only big problem I have with device is about battery.It doesn't last even 3 hours after full charge.
A31: Ek5z6ao | B31: 6YPEOk | C31: 45769.663 | D31: recCz1heG9HYapz1Z | E31: 10 | H31: Yes | I31: Yes | J31: Yes
A32: GxKvb5p | B32: JrovLR | C32: 45769.664 | D32: recqipYF4bAylKqe7 | E32: 6 | H32: Yes | I32: Yes | J32: No | K32: No, I have never looked for customer care | L32: 0 | M32: No | N32: Yes, and I am satisfied with the MoApp | O32: MoPhones App | P32: Yes | Q32: 0
A33: J9dKoXo | B33: 2YoGkD | C33: 45769.665 | D33: recbprJ3ndI6F0BhS | E33: 7 | H33: No | I33: Yes | J33: Yes | K33: Yes | L33: Someday I texted WhatsApp | M33: Yes | N33: Yes, and I am satisfied with the MoApp | O33: Reach Out via a Sales Agent | P33: No | Q33: NA
A34: yPNZ1pW | B34: gVz6Yd | C34: 45769.665 | D34: recO4cc15FMgzK9Jf | E34: 5 | H34: Yes | I34: No | J34: Yes | K34: Yes | L34: Weekends | M34: No | N34: No, I have never used it | O34: Reach Out via a Sales Agent | P34: Yes | Q34: Weekend
A35: jabDvGE | B35: NxP2RN | C35: 45769.665 | D35: recz6bPleTRitJUVS | E35: 3 | H35: Yes | I35: No | J35: Yes | K35: Yes | L35: I came to your shop with a complain about the phone battery bt bt instead of charging it, they gave me back the phone with the problem | M35: Yes | N35: No, I have never used it | O35: Phone Call – +254 728 444 442 or +254 709 924 404 | P35: Yes | Q35: No
A36: VLjENej | B36: gVz6z1 | C36: 45769.666 | D36: receqs5xvBzt3P9sN | E36: 8 | H36: Yes | I36: Yes | J36: No | K36: No | L36: have always been satisfied. | M36: No | N36: Yes, and I am satisfied with the MoApp | O36: Phone Call – +254 728 444 442 or +254 709 924 404 | P36: Yes | Q36: despite the challenge have had, am equally satisfied with your services.
A37: LZz1OB2 | B37: qqz1o7 | C37: 45769.666 | D37: rec9xhHoNXXxZVhm1 | E37: 6 | H37: Yes | I37: Yes | J37: No | K37: No | L37: T | M37: Yes | N37: Yes, but I am not satisfied with the MoApp | O37: Phone Call – +254 728 444 442 or +254 709 924 404 | P37: No | Q37: The MoApp should show the history of all transactions relating to a device payment.
A38: pbdxZrq | B38: BYeWY1 | C38: 45769.666 | D38: rect7DnuaYY5R6mKZ | E38: 8 | H38: Yes | I38: Yes | J38: No | K38: No | L38: I love ur phones | M38: No | N38: Yes, and I am satisfied with the MoApp | O38: Phone Call – +254 728 444 442 or +254 709 924 404 | P38: No | Q38: Goodservices viva!!
A39: Zjo5QEy | B39: 6YPE0A | C39: 45769.667 | D39: recLaXBaXTBTK6jWH | E39: 10 | H39: Yes | I39: Yes | J39: No | K39: No | L39: 😁 | M39: No | N39: No, I have never used it | O39: Phone Call – +254 728 444 442 or +254 709 924 404 | P39: Yes | Q39: 😎😮‍💨
A40: yPNZ71x | B40: 7YEkqL | C40: 45769.667 | D40: recJKLuwWfZr7TL15 | E40: 8 | H40: Yes | I40: Yes
A41: PdDjPGB | B41: ZAeBjy | C41: 45769.667 | D41: recrJt7yyQsVpOkQI | E41: 9 | H41: Yes | I41: Yes | J41: No | K41: No | L41: No | M41: No | N41: No, I have never used it | O41: Phone Call – +254 728 444 442 or +254 709 924 404 | P41: No | Q41: Excellent performance in all aspects.
A42: RGdKVNJ | B42: OZExaa | C42: 45769.668 | D42: rec1ZRnYchBJhvsCt | E42: 4 | H42: Yes | I42: Yes | J42: No | K42: No | L42: Okay the challenge am facing is in form of a question: Why is it that I can't go to YouTube even I selected it, it doesn't play so how can you help me there plz?. | M42: No | N42: Yes, and I am satisfied with the MoApp | O42: Reach Out via a Sales Agent | P42: No | Q42: No am just thankful for you people coz when I encounter a problem and reach out you are always available to sort me out thank you so,so much.
A43: dWNqRGz | B43: a1zMYW | C43: 45769.669 | D43: rec2TngHkBitHsQXn | E43: 9 | H43: Yes | I43: Yes | J43: Yes | K43: Yes | L43: Had asked for 3 days unlock but it locked within one day | M43: No | N43: Yes, and I am satisfied with the MoApp | O43: Phone Call – +254 728 444 442 or +254 709 924 404 | P43: Yes | Q43: Nothing
A44: VLjEx6l | B44: x7zWdE | C44: 45769.669 | D44: rec0ldrXhYF7VIQus | E44: 10 | H44: Yes | I44: Yes | J44: No | K44: Yes | L44: I don't like you people disconnect my phone on Monday | M44: No | N44: Yes, and I am satisfied with the MoApp | O44: Phone Call – +254 728 444 442 or +254 709 924 404 | P44: No | Q44: Nothing
A45: jabDErR | B45: rQYZAL | C45: 45769.669 | D45: recEK2nhHTyHdByC8 | E45: 8 | H45: Yes | I45: Yes | J45: No | K45: Yes | L45: Pick phone call better | M45: No | N45: No, I have never used it | O45: Free SMS – 25044 | P45: No | Q45: How private is my data? If indeed you review our feedback contact me with an answer.
A46: 81zo2dx | B46: x7zW6y | C46: 45769.669 | D46: recpTCQASRig7Tylw | E46: 10 | H46: Yes | I46: Yes | J46: No | K46: No
A47: rjBygL5 | B47: Jro4YJ | C47: 45769.669 | D47: recAASzdygMslxkcL | E47: 9 | H47: Yes | I47: Yes | J47: Yes | K47: No
A48: GNVKNZ | B48: LNYObO | C48: 45769.671 | D48: recjLCHYg0W63oFyq | E48: 9 | H48: Yes | I48: Yes | J48: No | K48: No | L48: I have never encountered any problem | M48: No | N48: No, I have never used it | O48: Reach Out via a Sales Agent | P48: No | Q48: I really appreciate the sales lady for the good work she did and helping out when i was purchasing the device 👍
A49: GxKvkoz | B49: O9LMda | C49: 45769.671 | D49: recOeT48Om69GV04r | E49: 5 | H49: Yes | I49: Yes | J49: No | K49: Yes | L49: Texts are not replied at all | M49: Yes | N49: Yes, and I am satisfied with the MoApp | O49: Phone Call – +254 728 444 442 or +254 709 924 404 | P49: No | Q49: Nothing
A50: Xxrl9Yd | B50: jrzV2R | C50: 45769.671 | D50: receZqSPKKw8UDIKZ | E50: 10 | H50: Yes | I50: Yes | J50: No | K50: No | L50: No | M50: No | N50: Yes, and I am satisfied with the MoApp | O50: Phone Call – +254 728 444 442 or +254 709 924 404 | P50: No | Q50: I will definitely refer someone
A51: KYeQOA8 | B51: 7YEkGa | C51: 45769.672 | D51: recn0q1aDa7KmcSx8 | E51: 10 | H51: Yes | I51: Yes | J51: No | K51: No | L51: not at all | M51: No | N51: Yes, and I am satisfied with the MoApp | O51: MoPhones App | P51: No | Q51: well organized
A52: J9dKG2d | B52: rQYZql | C52: 45769.672 | D52: recZlwbPcb948kWi0 | E52: 1 | H52: Yes | I52: Yes | J52: No | K52: No | L52: Switching off phone if no payment has not been done | M52: No | N52: Yes, and I am satisfied with the MoApp | O52: Free SMS – 25044 | P52: No | Q52: No any other
A53: ODl1raY | B53: OZEN8g | C53: 45769.672 | D53: recpAMvI9BVLq1BIk | E53: 0 | H53: Yes | I53: Yes | J53: Yes | K53: No | L53: Improve on unlocked phones
A54: q4aZp48 | B54: G40OMj | C54: 45769.672 | D54: recLLYUeTfcWFZq8P | H54: No | I54: Yes
A55: gDejpDM | B55: 2YoWAV | C55: 45769.673 | D55: recAx68tGudE5z4bl | E55: 10 | H55: Yes | I55: Yes | J55: Yes | K55: No | L55: No challenge | M55: No | N55: Yes, and I am satisfied with the MoApp | O55: MoPhones App | P55: Yes | Q55: N/A
A56: 68eJ9jA | B56: oZzPM1 | C56: 45769.674 | D56: recnPnRd0SWb2mvlT | E56: 10 | H56: Yes | I56: Yes | J56: No | K56: No | L56: Referred a friend but didnt get my discount | M56: No | N56: Yes, and I am satisfied with the MoApp | O56: Phone Call – +254 728 444 442 or +254 709 924 404 | P56: No | Q56: No
A57: 81zoWbz | B57: M2V4Qp | C57: 45769.675 | D57: recyRMj9xxAynZxRG | E57: 1 | H57: Yes | I57: Yes
A58: QKM2XlG | B58: pNzENb | C58: 45769.676 | D58: recnoKCiqFeiWsmFx | E58: 7 | H58: Yes | I58: Yes | J58: No | K58: Yes | L58: No | M58: Yes | N58: Yes, and I am satisfied with the MoApp | O58: MoPhones App | P58: No | Q58: I need phone repaired
A59: J9dKgeY | B59: vazZJg | C59: 45769.676 | D59: recwqeSGspDARCPMk | E59: 6 | H59: No | I59: No | J59: No | K59: Yes | L59: I'm unable to download some applications. I get restricted by admin notifications | M59: No | N59: Yes, and I am satisfied with the MoApp | O59: Free SMS – 25044 | P59: No | Q59: Help me disable admin restrictions on my phone.
A60: obD6pr1 | B60: yb1QQp | C60: 45769.676 | D60: recHpffrBFmnnaIBH | E60: 10 | H60: Yes | I60: Yes | J60: No | K60: No | L60: Long call waits | M60: No | N60: Yes, and I am satisfied with the MoApp | O60: Phone Call – +254 728 444 442 or +254 709 924 404 | P60: No | Q60: It working well
A61: rjBypZN | B61: W6qW6a | C61: 45769.676 | D61: reck6CILqLGLsGpKs | E61: 5 | H61: No | I61: Yes | J61: No | K61: Yes | L61: When traveling outside the country I can not use other simcards on my phone | M61: No | N61: Yes, and I am satisfied with the MoApp | O61: Phone Call – +254 728 444 442 or +254 709 924 404 | P61: Yes | Q61: The phone was waterproof but when it dropped in water And motherboard got destroyed I was told to pay for that repair clearly that was misinformation and also in warranty I had just used the phone for three months
A62: D4K2YRN | B62: 0Yk9gN | C62: 45769.677 | D62: rec0JjOk4k9QBjUMA | E62: 10 | H62: Yes | I62: Yes | J62: No | K62: No | L62: No | M62: No | N62: Yes, and I am satisfied with the MoApp | O62: Phone Call – +254 728 444 442 or +254 709 924 404 | P62: No | Q62: Please support me in adding 2 days after the expiry of my account
A63: yPNZGRd | B63: AY9g0D | C63: 45769.677 | D63: recz9P2LdiWAYmkfD | E63: 9 | H63: Yes | I63: Yes | J63: No | K63: No | L63: I have not experienced any challenge but you should adjust your payments to be done daily not weekly | M63: Yes | N63: Yes, but I am not satisfied with the MoApp | O63: Phone Call – +254 728 444 442 or +254 709 924 404 | P63: Yes | Q63: I suggest daily payments
A64: pbdx9yE | B64: M2V49E | C64: 45769.677 | D64: recGimqA8tvYvh7FI | E64: 9 | H64: Yes | I64: Yes | J64: No | K64: No | L64: No challenge experienced | M64: No | N64: Yes, and I am satisfied with the MoApp | O64: Phone Call – +254 728 444 442 or +254 709 924 404 | P64: No | Q64: Am okay
A65: LZz1yJp | B65: VaNKQy | C65: 45769.678 | D65: recjmq1ePLQnoBUWg | E65: 10 | H65: Yes | I65: Yes | J65: No | K65: No | L65: No applicable | M65: No | N65: Yes, and I am satisfied with the MoApp | O65: Phone Call – +254 728 444 442 or +254 709 924 404 | P65: No | Q65: No applicable
A66: BzK45ye | B66: GVbZqz | C66: 45769.678 | D66: recflB5Ag0Odf6LTN | E66: 5
A67: 44BXdQB | B67: 5YV7Rb | C67: 45769.679 | D67: reczlWsMPQNj2ZuLG | E67: 6 | H67: Yes | I67: No | J67: Yes | K67: Yes | L67: I had an issue whereby my device battery bulged causing the screen to break and when I took it for fixing with warranty it was never replaced I now use a phone which has a cracked screen and the on screen fingerprints is no longer functional. | M67: Yes | N67: Yes, and I am satisfied with the MoApp | O67: MoPhones App | P67: No | Q67: N/A
A68: VLjEy76 | B68: 7YEyJ9 | C68: 45769.679 | D68: recgC6NF6aU6ykuWP | E68: 10 | H68: Yes | I68: Yes | J68: Yes | K68: No | L68: No | M68: No | N68: Yes, and I am satisfied with the MoApp | O68: Free SMS – 25044 | P68: Yes | Q68: None
A69: NpD5y5G | B69: NxPjab | C69: 45769.68 | D69: recNzVJ7ttBMXABMd | E69: 4 | H69: No | I69: Yes | J69: No | K69: No, I have never looked for customer care | L69: My device at times has speaker issues | M69: Yes | N69: No, I have never used it | O69: Phone Call – +254 728 444 442 or +254 709 924 404 | P69: No | Q69: How do I use warranty coz my phone has speaker issue at times
A70: BzK4lE5 | B70: GVbZyL | C70: 45769.68 | D70: rec5s4VrSTy6etqE2 | E70: 8 | H70: Yes | I70: Yes | J70: No | K70: No | L70: None | M70: No | N70: No, I have never used it | O70: Phone Call – +254 728 444 442 or +254 709 924 404 | P70: No | Q70: None
A71: xXjxB8k | B71: 4YOMPo | C71: 45769.68 | D71: rec0ITuqc7Hbmh5I0 | E71: 9 | H71: Yes | I71: Yes | J71: Yes | K71: No | L71: So far so good | M71: No | N71: Yes, and I am satisfied with the MoApp | O71: Phone Call – +254 728 444 442 or +254 709 924 404 | P71: No | Q71: Maybe due to cureent economic times the installmwnts couod be atleast 1300 or there aboout, plus also consedaration on not locking phone before pay days, the deffier from.one customer to the other, mine is on 7th
A72: obD61R1 | B72: AY9ENz | C72: 45769.681 | D72: recYAvE5PT3yCiZDq | E72: 4 | H72: No | I72: No | J72: No | K72: No | L72: My phone has issues already
A73: 81zoyLA | B73: eGzVjk | C73: 45769.681 | D73: rectqITkbI5eY5Jb0 | E73: 10 | H73: Yes | I73: Yes | J73: No | K73: No | L73: No I have never experienced any challenge | M73: No | N73: Yes, and I am satisfied with the MoApp | O73: Phone Call – +254 728 444 442 or +254 709 924 404 | P73: No | Q73: None at the moment
A74: VLjEALJ | B74: PNr7g1 | C74: 45769.681 | D74: reckiVrQkFIioiJEJ | E74: 10 | H74: Yes | I74: Yes | J74: No | K74: No | L74: None | M74: Yes | N74: Yes, and I am satisfied with the MoApp | O74: Phone Call – +254 728 444 442 or +254 709 924 404 | P74: No | Q74: My battery is not last for long
A75: D4K2Pzj | B75: oZzqZP | C75: 45769.681 | D75: recKY4tcNrxoVVP81 | E75: 0 | H75: No | I75: Yes | J75: No | K75: Yes | L75: I tried contacting one of your whatsapp number concerning your phone which I'm using, I didn't get a response | M75: No | N75: Yes, and I am satisfied with the MoApp | O75: MoPhones App | P75: Yes | Q75: No
A76: 2EB85v9 | B76: rQYea2 | C76: 45769.681 | D76: recZt7pRX0FTdSggL | E76: 10 | H76: No | I76: No | J76: No | K76: No, I have never looked for customer care | L76: None | M76: No | N76: Yes, and I am satisfied with the MoApp | O76: Phone Call – +254 728 444 442 or +254 709 924 404 | P76: No | Q76: I am deeply concerned that MoPhone may be accessing my phone without my consent. On several occasions, I’ve noticed unusual activity such as apps opening and closing on their own, scrolling happening without my input, and my chats being accessed — all while I have no control. This is both alarming and unsettling. I would appreciate it if you could look into this matter and clarify what might be causing such occurrences.
A77: jabD2KJ | B77: jrzjkY | C77: 45769.681 | D77: recOF9e6eGRiYcPxy | E77: 10 | H77: Yes | I77: Yes | J77: No | K77: No | L77: Everything is okay but i feelclike you could.be adding someone a day before the locking of the device or a reminder for it... | M77: Yes | N77: Yes, and I am satisfied with the MoApp | O77: Phone Call – +254 728 444 442 or +254 709 924 404
A78: XxrlkNg | B78: jrzKa9 | C78: 45769.682 | D78: recvc39EvMYnkBKy9 | E78: 10 | H78: Yes | I78: Yes | J78: No | K78: No, I have never looked for customer care | L78: Na | M78: No | N78: Yes, but I am not satisfied with the MoApp | O78: Phone Call – +254 728 444 442 or +254 709 924 404 | P78: No | Q78: NA
A79: NpD5QGp | B79: 6YPqxJ | C79: 45769.683 | D79: rect5BpHLRHHJ1biS | E79: 4 | H79: Yes | I79: Yes
A80: 44BXyv5 | B80: vazlZQ | C80: 45769.683 | D80: recl5jFVrJP8eOklC | E80: 10 | H80: Yes | I80: Yes | J80: No | K80: No | L80: Very nice | M80: No | N80: Yes, and I am satisfied with the MoApp | O80: Phone Call – +254 728 444 442 or +254 709 924 404 | P80: Yes | Q80: No
A81: GxKv46o | B81: M2VWyk | C81: 45769.683 | D81: recLzhGQm212rd3Zg | E81: 4 | H81: Yes | I81: No | J81: Yes | K81: Yes | L81: I once forgot my phone lock password and you guys mkaona mnikamue proper | M81: No | N81: Yes, and I am satisfied with the MoApp | O81: Phone Call – +254 728 444 442 or +254 709 924 404 | P81: Yes | Q81: A question .........nkimaliza payment will you be still managing this handset?
A82: gDej1VN | B82: 5YVN9Q | C82: 45769.683 | D82: rec1I4Edrs4d5BdhW | E82: 10 | H82: Yes | I82: Yes | J82: No | K82: No | L82: None | M82: No | N82: No, I have never used it | O82: Phone Call – +254 728 444 442 or +254 709 924 404 | P82: No | Q82: None
A83: vGrjvjl | B83: GVbMDZ | C83: 45769.683 | D83: rec8xC0dTeg51IJAv | E83: 7 | H83: Yes | I83: Yes | J83: Yes | K83: No | L83: No challenge
A84: PdDjePV | B84: 6YPq85 | C84: 45769.683 | D84: rec3F60HEZQdHj8kA | E84: 10 | H84: Yes | I84: Yes | J84: No | K84: No | L84: It's better keep up | M84: No | N84: Yes, and I am satisfied with the MoApp | O84: MoPhones App | P84: No | Q84: It's better
A85: RGdKaAv | B85: 1yEoBL | C85: 45769.683 | D85: recvfQIzxKzdeDBFb | E85: 9 | H85: Yes | I85: Yes | J85: No | K85: Yes | L85: Online chats don't respond after hours | M85: Yes | N85: Yes, and I am satisfied with the MoApp | O85: MoPhones App | P85: No | Q85: Need fast recovery time
A86: VLjEAOE | B86: AY9kvy | C86: 45769.684 | D86: recFgufIW70gKSaF7 | E86: 0 | H86: No | I86: No | J86: Yes | K86: No | L86: I don't know if it's the phone it self because it works very slowly | M86: Yes | N86: Yes, but I am not satisfied with the MoApp | O86: MoPhones App | P86: No | Q86: I don't like the way thud phone processes it's data because it's very slow and sometimes it hangs and there a lot of space here
A87: BzK4lWY | B87: OZER5a | C87: 45769.684 | D87: rec8l8Z3r5ZlxJgYm | E87: 5 | H87: Yes | I87: Yes | J87: Yes | K87: No | L87: Payment had not reflected | M87: Yes | N87: No, I have never used it | O87: Phone Call – +254 728 444 442 or +254 709 924 404 | P87: Yes | Q87: Offer some discounts once we pay on time
A88: PdDjWjB | B88: 1YRjvp | C88: 45769.684 | D88: recQqKMpvU6GUh8jS | E88: 8 | H88: Yes | I88: Yes | J88: Yes | K88: No | L88: I was going through a financial crisis and how to improve is just to work hard | M88: No | N88: Yes, and I am satisfied with the MoApp | O88: MoPhones App | P88: No | Q88: No
A89: dWNq1BV | B89: 7zvQVZ | C89: 45769.684 | D89: reccz2gPGEAGFehDC | E89: 9 | H89: Yes | I89: Yes | J89: No | K89: No | L89: None | M89: No | N89: Yes, and I am satisfied with the MoApp | O89: Phone Call – +254 728 444 442 or +254 709 924 404 | P89: No | Q89: I am satisfied
A90: yPNZRJ0 | B90: PNr7Le | C90: 45769.684 | D90: recdvLol2P0WDO0vl | E90: 10 | H90: Yes | I90: Yes | J90: No | K90: No | L90: I have nothing to add | M90: Yes | N90: No, I have never used it | O90: MoPhones App | P90: No | Q90: Moapp is not available in apple
A91: Ek5zrl4 | B91: EG6pvN | C91: 45769.684 | D91: recVMoFHf252ywAMP | E91: 10 | H91: Yes | I91: Yes | J91: No | K91: No | L91: Nothing | M91: No | N91: Yes, and I am satisfied with the MoApp | O91: Phone Call – +254 728 444 442 or +254 709 924 404 | P91: No | Q91: I appreciate
A92: aQeNPZW | B92: ljzp9X | C92: 45769.684 | D92: rec0CsNk3ewkMBGBu | E92: 3
A93: dWNq4xq | B93: 7YEQpL | C93: 45769.685 | D93: recUXVKFRJ94o0Xtx | E93: 5 | H93: Yes | I93: Yes | J93: No | K93: Yes | L93: Being told to take photos for the second time if I want another phone yet you have my details
A94: Zjo5LXo | B94: jrzKKa | C94: 45769.685 | D94: rec9MogCjS6ixcJtm | E94: 1
A95: xXjxLay | B95: X7Qj2O | C95: 45769.686 | D95: recfGn21idkkksfKD | E95: 10 | H95: Yes | I95: Yes | J95: No | K95: No | L95: Understand in economics situation | M95: Yes | N95: Yes, but I am not satisfied with the MoApp | O95: Phone Call – +254 728 444 442 or +254 709 924 404 | P95: Yes | Q95: Poor customer service
A96: rjBybV5 | B96: OZERrA | C96: 45769.686 | D96: recrmy7WSvZjq30aU | E96: 10 | H96: Yes | I96: Yes | J96: Yes | K96: No | L96: N/A | M96: No | N96: Yes, and I am satisfied with the MoApp | O96: Free SMS – 25044 | P96: No | Q96: N/A
A97: KYeQN9M | B97: DoaQ25 | C97: 45769.687 | D97: recpY4yLXU4vvvMrB | E97: 10 | H97: Yes | I97: Yes | J97: Yes | K97: No
A98: rjBybNp | B98: 4YO5BB | C98: 45769.688 | D98: recQwlUSYREf8Oq80 | E98: 5 | H98: No | I98: Yes | J98: No | K98: No | L98: No challenge at the moment | M98: No | N98: Yes, and I am satisfied with the MoApp | O98: MoPhones App | P98: No | Q98: No
A99: q4aZ7B2 | B99: VaNrxl | C99: 45769.688 | D99: recYaOD7HcWZhQqDQ | E99: 3 | H99: No | I99: No | J99: No | K99: Yes | L99: My phone has been overheating from day 1 till now. No resolve. I have a small baby n can't make it to the offices in town. Bottleneck | M99: Yes | N99: Yes, and I am satisfied with the MoApp | O99: Reach Out via a Sales Agent | P99: No | Q99: Payment you guys are not late. Quality of phone, battery, not great. For the sum of money we pay, the phones could DEFINITELY be better
A100: Ek5zeDX | B100: W6qyYk | C100: 45769.69 | D100: recF27j93eHkcruZo | E100: 8 | H100: Yes | I100: Yes | J100: No | K100: No, I have never looked for customer care | L100: None | M100: No | N100: No, I have never used it | O100: Phone Call – +254 728 444 442 or +254 709 924 404 | P100: No | Q100: Would recommend mo phones its a 10/10
...

Sheet Distinct
A1: Submission ID | B1: Respondent ID | C1: Submitted at | D1: Loan Id | E1: Using a scale from 0 (not likely) to 10 (very likely), how likely are you to recommend ABC Phones to friends or family? | F1: What is the main reason for your score? | G1: What is one thing we could do to improve your experience with us? | H1: Are you happy with the quality and performance of your device? | I1: Are you happy with the service and support provided by ABC Phones? | J1: Have you ever experienced a delay in your payment reflecting in your ABC account? | K1: Have you ever had difficulty getting assistance from ABC Phones customer support when needed? | L1: (If Yes) – Please describe the challenge you faced and how we can improve your experience. | M1: Have you experienced any battery-related issues with your MoPhones device? | N1: Have you used the MoPhones app (MoApp) to manage your account or make payments? | O1: Which communication channel do you prefer when contacting MoPhones for inquiries or support? | P1: Have you ever had your phone lock despite making a payment on time? | Q1: Any other Feedback?
A2: BzK4Q11 | B2: k4z1Y6 | C2: 45769.635 | D2: rec2FCxHhqXw6aKRU | E2: 6 | H2: Yes | I2: Yes | J2: Yes | K2: Yes | L2: Unlocking my phone | M2: No | N2: Yes, and I am satisfied with the MoApp | O2: MoPhones App | P2: Yes | Q2: N/A
A3: b59V45Z | B3: AY9GMk | C3: 45769.637 | D3: recQcLWbPcep18Wdw | E3: 10 | H3: Yes | I3: Yes | J3: No | K3: No | L3: Response team always on time | M3: No | N3: Yes, and I am satisfied with the MoApp | O3: Free SMS – 25044 | P3: No | Q3: Would like to upgrade once I'm done with this loan
A4: GxKvYKO | B4: eGz8Ek | C4: 45769.647 | D4: recei9UEU0e5F9HuG | E4: 5 | H4: No | I4: No | J4: No | K4: Yes | L4: I bought a Samsung A42 which has fingerprint lock that doesn't work since I bought it from ABC, I took it back and it's wasn't fixed.. Then the Phone has an on and Off network issues | M4: No | N4: Yes, and I am satisfied with the MoApp | O4: Phone Call – +254 728 444 442 or +254 709 924 404 | P4: Yes | Q4: Good service and efficient response
A5: A7KP49z | B5: LjOx7j | C5: 45769.653 | D5: recosDWAJvWzAKgLv | E5: 1 | H5: No | I5: No | J5: Yes | K5: Yes | L5: Delays | M5: Yes | N5: Yes, but I am not satisfied with the MoApp
A6: 81zo6pr | B6: 7YE0RR | C6: 45769.653 | D6: recTJng0Mj0dJP1kv | E6: 1 | H6: No | I6: No | J6: Yes | K6: Yes | L6: Not satisfied with my phone | M6: Yes | N6: Yes, but I am not satisfied with the MoApp | O6: MoPhones App | P6: Yes | Q6: Not satisfied with my phone
A7: xXjxR5J | B7: RQjeLp | C7: 45769.653 | D7: recPKFOtpkS0z9Kpp | E7: 10 | H7: Yes | I7: Yes | J7: No | K7: No | L7: . | M7: No | N7: Yes, and I am satisfied with the MoApp | O7: Phone Call – +254 728 444 442 or +254 709 924 404 | P7: No | Q7: .
A8: GxKvQ6L | B8: ljz2Mo | C8: 45769.653 | D8: rechy4Nf0Ihxrdy85 | E8: 10
A9: rjBykB2 | B9: k4zjvo | C9: 45769.654 | D9: recayIesPKGAMilkX | E9: 0
A10: 5B4KeaM | B10: k4zjZJ | C10: 45769.654 | D10: rec86PnPzgTEunR4Q | E10: 9 | H10: No | I10: No | J10: Yes | K10: Yes | L10: There is a lot to be | M10: No | N10: Yes, and I am satisfied with the MoApp | O10: MoPhones App | P10: Yes | Q10: None
A11: 5B4Kp16 | B11: rQY9pN | C11: 45769.656 | D11: recJKsUBTzHl4IGK3 | E11: 10 | H11: Yes | I11: Yes | J11: Yes | K11: No, I have never looked for customer care | L11: N/A | M11: No | N11: Yes, and I am satisfied with the MoApp | O11: Phone Call – +254 728 444 442 or +254 709 924 404 | P11: No | Q11: N/A
A12: eqDZYBO | B12: AY9RGD | C12: 45769.656 | D12: recUmt3DbYL0gb025 | E12: 10 | H12: Yes | I12: Yes | J12: No | K12: No | L12: None | M12: No | N12: Yes, and I am satisfied with the MoApp | O12: Reach Out via a Sales Agent | P12: No | Q12: None
A13: aQeNaYv | B13: yRD5Dg | C13: 45769.656 | D13: recVOllpG6mFoGtaV | E13: 8 | H13: No | I13: Yes | J13: No | K13: No | L13: Battery can't store charge I need a replaced of battery | M13: Yes | N13: Yes, and I am satisfied with the MoApp | O13: Phone Call – +254 728 444 442 or +254 709 924 404 | P13: No | Q13: Kindly exchange my battery
A14: dWNqK2d | B14: gVzV5M | C14: 45769.656 | D14: reciMIpVjO2lBzHt8 | E14: 7 | H14: Yes | I14: Yes | J14: Yes | K14: No | L14: Payment terms are harsh | M14: No | N14: No, I have never used it | O14: Phone Call – +254 728 444 442 or +254 709 924 404 | P14: Yes | Q14: You need to check on payment terms
A15: WOr9jYJ | B15: AY9RN0 | C15: 45769.656 | D15: receJwqtM49LS8gE8 | E15: 10 | H15: Yes | I15: Yes | J15: Yes | K15: No, I have never looked for customer care | L15: No | M15: No | N15: No, I have never used it | O15: Phone Call – +254 728 444 442 or +254 709 924 404 | P15: Yes | Q15: Am happy for your service
A16: zxNX1Q8 | B16: 4YO00O | C16: 45769.656 | D16: recB2N3ejw9jeBo4l | E16: 0 | H16: No | I16: No | J16: Yes | K16: Yes | L16: My phone is not working despite payment | M16: Yes | N16: Yes, and I am satisfied with the MoApp | O16: Phone Call – +254 728 444 442 or +254 709 924 404 | P16: Yes | Q16: My phone has a charging problem since
A17: jabDkpQ | B17: gVzPBK | C17: 45769.657 | D17: recK9QseqaimraXBE | E17: 8 | H17: Yes | I17: Yes | J17: Yes | K17: No | L17: Have a 24/7 customer care services | M17: Yes | N17: Yes, but I am not satisfied with the MoApp | O17: Phone Call – +254 728 444 442 or +254 709 924 404 | P17: No | Q17: No
A18: PdDjkDx | B18: gVz85l | C18: 45769.658 | D18: rectavMBbkg1rwXIl | E18: 10 | H18: Yes | I18: Yes | J18: No | K18: No
A19: MeDK74X | B19: 8YrbNl | C19: 45769.659 | D19: recu8gML0JT6Cd9ES | E19: 3 | H19: No | I19: No | J19: Yes | K19: Yes | M19: Yes | N19: Yes, but I am not satisfied with the MoApp | O19: MoPhones App | P19: No | Q19: Improve in your app
A20: vGrjKyl | B20: 4YOlvb | C20: 45769.659 | D20: recHDnVDRlfvts5dQ | E20: 6 | H20: Yes | I20: Yes | J20: No | K20: Yes | L20: MOPHONES | M20: Yes | N20: Yes, and I am satisfied with the MoApp | O20: Free SMS – 25044 | P20: No | Q20: Nome
A21: XxrlzDL | B21: Qq4NYg | C21: 45769.66 | D21: recvDdpWZLA2VCChR | E21: 10 | H21: Yes | I21: No | J21: No | K21: Yes | L21: Support center should work 24\7 | M21: No | N21: No, I have never used it | O21: Phone Call – +254 728 444 442 or +254 709 924 404 | P21: Yes | Q21: No
A22: zxNXL0q | B22: AY9M4N | C22: 45769.66 | D22: rec7AnOdegQgCwyT6 | E22: 8 | H22: Yes | I22: Yes | J22: Yes | K22: No | L22: Avoid delay while approving a grace period | M22: Yes | N22: Yes, and I am satisfied with the MoApp | O22: Free SMS – 25044 | P22: Yes | Q22: None
A23: Y5RDkx6 | B23: k4z8rZ | C23: 45769.66 | D23: recIZZtnG0LN1MpqF | E23: 9 | H23: Yes | I23: Yes | J23: Yes | K23: Yes | L23: You don't accept calls
A24: 7RblMyZ | B24: ljz8GB | C24: 45769.66 | D24: recAyJ8v8VJuecwtB | E24: 9 | H24: Yes | I24: Yes | J24: No | K24: No
A25: kd9av2R | B25: OZEx27 | C25: 45769.661 | D25: recjPY1G5I3fQxMOn | E25: 8 | H25: Yes | I25: Yes | J25: No | K25: No | L25: Non | M25: No | N25: Yes, but I am not satisfied with the MoApp | O25: Free SMS – 25044 | P25: No | Q25: No
A26: 2EB87Zg | B26: dozJVr | C26: 45769.662 | D26: rec4fZqbuemGwnwZF | E26: 10 | H26: Yes | I26: Yes | J26: No | K26: No | L26: No | M26: Yes | N26: No, I have never used it | O26: Phone Call – +254 728 444 442 or +254 709 924 404 | P26: No | Q26: No
A27: MeDKVb8 | B27: Jrovpz | C27: 45769.662 | D27: recl4egRn2rQH4mO0 | H27: Yes | I27: Yes
A28: Y5RD9G0 | B28: Jrov97 | C28: 45769.662 | D28: recQJWCGAZ7yuy0k7 | E28: 8 | H28: Yes | I28: Yes | J28: Yes | K28: No | L28: No
A29: 9qXG4Z4 | B29: GVbAez | C29: 45769.662 | D29: rec6r5JWy61FR24fB | E29: 9 | H29: Yes | I29: Yes | J29: No | K29: No
A30: xXjxvbv | B30: RQjqej | C30: 45769.662 | D30: recEx6e0qdGKb242p | E30: 10 | H30: Yes | I30: Yes | J30: No | K30: No | L30: No | M30: Yes | N30: Yes, and I am satisfied with the MoApp | O30: MoPhones App | P30: No | Q30: Had some challenges at the beginning but they were sorted.The only big problem I have with device is about battery.It doesn't last even 3 hours after full charge.
A31: Ek5z6ao | B31: 6YPEOk | C31: 45769.663 | D31: recCz1heG9HYapz1Z | E31: 10 | H31: Yes | I31: Yes | J31: Yes
A32: GxKvb5p | B32: JrovLR | C32: 45769.664 | D32: recqipYF4bAylKqe7 | E32: 6 | H32: Yes | I32: Yes | J32: No | K32: No, I have never looked for customer care | L32: 0 | M32: No | N32: Yes, and I am satisfied with the MoApp | O32: MoPhones App | P32: Yes | Q32: 0
A33: J9dKoXo | B33: 2YoGkD | C33: 45769.665 | D33: recbprJ3ndI6F0BhS | E33: 7 | H33: No | I33: Yes | J33: Yes | K33: Yes | L33: Someday I texted WhatsApp | M33: Yes | N33: Yes, and I am satisfied with the MoApp | O33: Reach Out via a Sales Agent | P33: No | Q33: NA
A34: yPNZ1pW | B34: gVz6Yd | C34: 45769.665 | D34: recO4cc15FMgzK9Jf | E34: 5 | H34: Yes | I34: No | J34: Yes | K34: Yes | L34: Weekends | M34: No | N34: No, I have never used it | O34: Reach Out via a Sales Agent | P34: Yes | Q34: Weekend
A35: jabDvGE | B35: NxP2RN | C35: 45769.665 | D35: recz6bPleTRitJUVS | E35: 3 | H35: Yes | I35: No | J35: Yes | K35: Yes | L35: I came to your shop with a complain about the phone battery bt bt instead of charging it, they gave me back the phone with the problem | M35: Yes | N35: No, I have never used it | O35: Phone Call – +254 728 444 442 or +254 709 924 404 | P35: Yes | Q35: No
A36: VLjENej | B36: gVz6z1 | C36: 45769.666 | D36: receqs5xvBzt3P9sN | E36: 8 | H36: Yes | I36: Yes | J36: No | K36: No | L36: have always been satisfied. | M36: No | N36: Yes, and I am satisfied with the MoApp | O36: Phone Call – +254 728 444 442 or +254 709 924 404 | P36: Yes | Q36: despite the challenge have had, am equally satisfied with your services.
A37: LZz1OB2 | B37: qqz1o7 | C37: 45769.666 | D37: rec9xhHoNXXxZVhm1 | E37: 6 | H37: Yes | I37: Yes | J37: No | K37: No | L37: T | M37: Yes | N37: Yes, but I am not satisfied with the MoApp | O37: Phone Call – +254 728 444 442 or +254 709 924 404 | P37: No | Q37: The MoApp should show the history of all transactions relating to a device payment.
A38: pbdxZrq | B38: BYeWY1 | C38: 45769.666 | D38: rect7DnuaYY5R6mKZ | E38: 8 | H38: Yes | I38: Yes | J38: No | K38: No | L38: I love ur phones | M38: No | N38: Yes, and I am satisfied with the MoApp | O38: Phone Call – +254 728 444 442 or +254 709 924 404 | P38: No | Q38: Goodservices viva!!
A39: Zjo5QEy | B39: 6YPE0A | C39: 45769.667 | D39: recLaXBaXTBTK6jWH | E39: 10 | H39: Yes | I39: Yes | J39: No | K39: No | L39: 😁 | M39: No | N39: No, I have never used it | O39: Phone Call – +254 728 444 442 or +254 709 924 404 | P39: Yes | Q39: 😎😮‍💨
A40: yPNZ71x | B40: 7YEkqL | C40: 45769.667 | D40: recJKLuwWfZr7TL15 | E40: 8 | H40: Yes | I40: Yes
A41: PdDjPGB | B41: ZAeBjy | C41: 45769.667 | D41: recrJt7yyQsVpOkQI | E41: 9 | H41: Yes | I41: Yes | J41: No | K41: No | L41: No | M41: No | N41: No, I have never used it | O41: Phone Call – +254 728 444 442 or +254 709 924 404 | P41: No | Q41: Excellent performance in all aspects.
A42: RGdKVNJ | B42: OZExaa | C42: 45769.668 | D42: rec1ZRnYchBJhvsCt | E42: 4 | H42: Yes | I42: Yes | J42: No | K42: No | L42: Okay the challenge am facing is in form of a question: Why is it that I can't go to YouTube even I selected it, it doesn't play so how can you help me there plz?. | M42: No | N42: Yes, and I am satisfied with the MoApp | O42: Reach Out via a Sales Agent | P42: No | Q42: No am just thankful for you people coz when I encounter a problem and reach out you are always available to sort me out thank you so,so much.
A43: dWNqRGz | B43: a1zMYW | C43: 45769.669 | D43: rec2TngHkBitHsQXn | E43: 9 | H43: Yes | I43: Yes | J43: Yes | K43: Yes | L43: Had asked for 3 days unlock but it locked within one day | M43: No | N43: Yes, and I am satisfied with the MoApp | O43: Phone Call – +254 728 444 442 or +254 709 924 404 | P43: Yes | Q43: Nothing
A44: VLjEx6l | B44: x7zWdE | C44: 45769.669 | D44: rec0ldrXhYF7VIQus | E44: 10 | H44: Yes | I44: Yes | J44: No | K44: Yes | L44: I don't like you people disconnect my phone on Monday | M44: No | N44: Yes, and I am satisfied with the MoApp | O44: Phone Call – +254 728 444 442 or +254 709 924 404 | P44: No | Q44: Nothing
A45: jabDErR | B45: rQYZAL | C45: 45769.669 | D45: recEK2nhHTyHdByC8 | E45: 8 | H45: Yes | I45: Yes | J45: No | K45: Yes | L45: Pick phone call better | M45: No | N45: No, I have never used it | O45: Free SMS – 25044 | P45: No | Q45: How private is my data? If indeed you review our feedback contact me with an answer.
A46: 81zo2dx | B46: x7zW6y | C46: 45769.669 | D46: recpTCQASRig7Tylw | E46: 10 | H46: Yes | I46: Yes | J46: No | K46: No
A47: rjBygL5 | B47: Jro4YJ | C47: 45769.669 | D47: recAASzdygMslxkcL | E47: 9 | H47: Yes | I47: Yes | J47: Yes | K47: No
A48: GNVKNZ | B48: LNYObO | C48: 45769.671 | D48: recjLCHYg0W63oFyq | E48: 9 | H48: Yes | I48: Yes | J48: No | K48: No | L48: I have never encountered any problem | M48: No | N48: No, I have never used it | O48: Reach Out via a Sales Agent | P48: No | Q48: I really appreciate the sales lady for the good work she did and helping out when i was purchasing the device 👍
A49: GxKvkoz | B49: O9LMda | C49: 45769.671 | D49: recOeT48Om69GV04r | E49: 5 | H49: Yes | I49: Yes | J49: No | K49: Yes | L49: Texts are not replied at all | M49: Yes | N49: Yes, and I am satisfied with the MoApp | O49: Phone Call – +254 728 444 442 or +254 709 924 404 | P49: No | Q49: Nothing
A50: Xxrl9Yd | B50: jrzV2R | C50: 45769.671 | D50: receZqSPKKw8UDIKZ | E50: 10 | H50: Yes | I50: Yes | J50: No | K50: No | L50: No | M50: No | N50: Yes, and I am satisfied with the MoApp | O50: Phone Call – +254 728 444 442 or +254 709 924 404 | P50: No | Q50: I will definitely refer someone
A51: KYeQOA8 | B51: 7YEkGa | C51: 45769.672 | D51: recn0q1aDa7KmcSx8 | E51: 10 | H51: Yes | I51: Yes | J51: No | K51: No | L51: not at all | M51: No | N51: Yes, and I am satisfied with the MoApp | O51: MoPhones App | P51: No | Q51: well organized
A52: J9dKG2d | B52: rQYZql | C52: 45769.672 | D52: recZlwbPcb948kWi0 | E52: 1 | H52: Yes | I52: Yes | J52: No | K52: No | L52: Switching off phone if no payment has not been done | M52: No | N52: Yes, and I am satisfied with the MoApp | O52: Free SMS – 25044 | P52: No | Q52: No any other
A53: ODl1raY | B53: OZEN8g | C53: 45769.672 | D53: recpAMvI9BVLq1BIk | E53: 0 | H53: Yes | I53: Yes | J53: Yes | K53: No | L53: Improve on unlocked phones
A54: q4aZp48 | B54: G40OMj | C54: 45769.672 | D54: recLLYUeTfcWFZq8P | H54: No | I54: Yes
A55: gDejpDM | B55: 2YoWAV | C55: 45769.673 | D55: recAx68tGudE5z4bl | E55: 10 | H55: Yes | I55: Yes | J55: Yes | K55: No | L55: No challenge | M55: No | N55: Yes, and I am satisfied with the MoApp | O55: MoPhones App | P55: Yes | Q55: N/A
A56: 68eJ9jA | B56: oZzPM1 | C56: 45769.674 | D56: recnPnRd0SWb2mvlT | E56: 10 | H56: Yes | I56: Yes | J56: No | K56: No | L56: Referred a friend but didnt get my discount | M56: No | N56: Yes, and I am satisfied with the MoApp | O56: Phone Call – +254 728 444 442 or +254 709 924 404 | P56: No | Q56: No
A57: 81zoWbz | B57: M2V4Qp | C57: 45769.675 | D57: recyRMj9xxAynZxRG | E57: 1 | H57: Yes | I57: Yes
A58: QKM2XlG | B58: pNzENb | C58: 45769.676 | D58: recnoKCiqFeiWsmFx | E58: 7 | H58: Yes | I58: Yes | J58: No | K58: Yes | L58: No | M58: Yes | N58: Yes, and I am satisfied with the MoApp | O58: MoPhones App | P58: No | Q58: I need phone repaired
A59: J9dKgeY | B59: vazZJg | C59: 45769.676 | D59: recwqeSGspDARCPMk | E59: 6 | H59: No | I59: No | J59: No | K59: Yes | L59: I'm unable to download some applications. I get restricted by admin notifications | M59: No | N59: Yes, and I am satisfied with the MoApp | O59: Free SMS – 25044 | P59: No | Q59: Help me disable admin restrictions on my phone.
A60: obD6pr1 | B60: yb1QQp | C60: 45769.676 | D60: recHpffrBFmnnaIBH | E60: 10 | H60: Yes | I60: Yes | J60: No | K60: No | L60: Long call waits | M60: No | N60: Yes, and I am satisfied with the MoApp | O60: Phone Call – +254 728 444 442 or +254 709 924 404 | P60: No | Q60: It working well
A61: rjBypZN | B61: W6qW6a | C61: 45769.676 | D61: reck6CILqLGLsGpKs | E61: 5 | H61: No | I61: Yes | J61: No | K61: Yes | L61: When traveling outside the country I can not use other simcards on my phone | M61: No | N61: Yes, and I am satisfied with the MoApp | O61: Phone Call – +254 728 444 442 or +254 709 924 404 | P61: Yes | Q61: The phone was waterproof but when it dropped in water And motherboard got destroyed I was told to pay for that repair clearly that was misinformation and also in warranty I had just used the phone for three months
A62: D4K2YRN | B62: 0Yk9gN | C62: 45769.677 | D62: rec0JjOk4k9QBjUMA | E62: 10 | H62: Yes | I62: Yes | J62: No | K62: No | L62: No | M62: No | N62: Yes, and I am satisfied with the MoApp | O62: Phone Call – +254 728 444 442 or +254 709 924 404 | P62: No | Q62: Please support me in adding 2 days after the expiry of my account
A63: yPNZGRd | B63: AY9g0D | C63: 45769.677 | D63: recz9P2LdiWAYmkfD | E63: 9 | H63: Yes | I63: Yes | J63: No | K63: No | L63: I have not experienced any challenge but you should adjust your payments to be done daily not weekly | M63: Yes | N63: Yes, but I am not satisfied with the MoApp | O63: Phone Call – +254 728 444 442 or +254 709 924 404 | P63: Yes | Q63: I suggest daily payments
A64: pbdx9yE | B64: M2V49E | C64: 45769.677 | D64: recGimqA8tvYvh7FI | E64: 9 | H64: Yes | I64: Yes | J64: No | K64: No | L64: No challenge experienced | M64: No | N64: Yes, and I am satisfied with the MoApp | O64: Phone Call – +254 728 444 442 or +254 709 924 404 | P64: No | Q64: Am okay
A65: LZz1yJp | B65: VaNKQy | C65: 45769.678 | D65: recjmq1ePLQnoBUWg | E65: 10 | H65: Yes | I65: Yes | J65: No | K65: No | L65: No applicable | M65: No | N65: Yes, and I am satisfied with the MoApp | O65: Phone Call – +254 728 444 442 or +254 709 924 404 | P65: No | Q65: No applicable
A66: BzK45ye | B66: GVbZqz | C66: 45769.678 | D66: recflB5Ag0Odf6LTN | E66: 5
A67: 44BXdQB | B67: 5YV7Rb | C67: 45769.679 | D67: reczlWsMPQNj2ZuLG | E67: 6 | H67: Yes | I67: No | J67: Yes | K67: Yes | L67: I had an issue whereby my device battery bulged causing the screen to break and when I took it for fixing with warranty it was never replaced I now use a phone which has a cracked screen and the on screen fingerprints is no longer functional. | M67: Yes | N67: Yes, and I am satisfied with the MoApp | O67: MoPhones App | P67: No | Q67: N/A
A68: VLjEy76 | B68: 7YEyJ9 | C68: 45769.679 | D68: recgC6NF6aU6ykuWP | E68: 10 | H68: Yes | I68: Yes | J68: Yes | K68: No | L68: No | M68: No | N68: Yes, and I am satisfied with the MoApp | O68: Free SMS – 25044 | P68: Yes | Q68: None
A69: NpD5y5G | B69: NxPjab | C69: 45769.68 | D69: recNzVJ7ttBMXABMd | E69: 4 | H69: No | I69: Yes | J69: No | K69: No, I have never looked for customer care | L69: My device at times has speaker issues | M69: Yes | N69: No, I have never used it | O69: Phone Call – +254 728 444 442 or +254 709 924 404 | P69: No | Q69: How do I use warranty coz my phone has speaker issue at times
A70: BzK4lE5 | B70: GVbZyL | C70: 45769.68 | D70: rec5s4VrSTy6etqE2 | E70: 8 | H70: Yes | I70: Yes | J70: No | K70: No | L70: None | M70: No | N70: No, I have never used it | O70: Phone Call – +254 728 444 442 or +254 709 924 404 | P70: No | Q70: None
A71: xXjxB8k | B71: 4YOMPo | C71: 45769.68 | D71: rec0ITuqc7Hbmh5I0 | E71: 9 | H71: Yes | I71: Yes | J71: Yes | K71: No | L71: So far so good | M71: No | N71: Yes, and I am satisfied with the MoApp | O71: Phone Call – +254 728 444 442 or +254 709 924 404 | P71: No | Q71: Maybe due to cureent economic times the installmwnts couod be atleast 1300 or there aboout, plus also consedaration on not locking phone before pay days, the deffier from.one customer to the other, mine is on 7th
A72: obD61R1 | B72: AY9ENz | C72: 45769.681 | D72: recYAvE5PT3yCiZDq | E72: 4 | H72: No | I72: No | J72: No | K72: No | L72: My phone has issues already
A73: 81zoyLA | B73: eGzVjk | C73: 45769.681 | D73: rectqITkbI5eY5Jb0 | E73: 10 | H73: Yes | I73: Yes | J73: No | K73: No | L73: No I have never experienced any challenge | M73: No | N73: Yes, and I am satisfied with the MoApp | O73: Phone Call – +254 728 444 442 or +254 709 924 404 | P73: No | Q73: None at the moment
A74: VLjEALJ | B74: PNr7g1 | C74: 45769.681 | D74: reckiVrQkFIioiJEJ | E74: 10 | H74: Yes | I74: Yes | J74: No | K74: No | L74: None | M74: Yes | N74: Yes, and I am satisfied with the MoApp | O74: Phone Call – +254 728 444 442 or +254 709 924 404 | P74: No | Q74: My battery is not last for long
A75: D4K2Pzj | B75: oZzqZP | C75: 45769.681 | D75: recKY4tcNrxoVVP81 | E75: 0 | H75: No | I75: Yes | J75: No | K75: Yes | L75: I tried contacting one of your whatsapp number concerning your phone which I'm using, I didn't get a response | M75: No | N75: Yes, and I am satisfied with the MoApp | O75: MoPhones App | P75: Yes | Q75: No
A76: 2EB85v9 | B76: rQYea2 | C76: 45769.681 | D76: recZt7pRX0FTdSggL | E76: 10 | H76: No | I76: No | J76: No | K76: No, I have never looked for customer care | L76: None | M76: No | N76: Yes, and I am satisfied with the MoApp | O76: Phone Call – +254 728 444 442 or +254 709 924 404 | P76: No | Q76: I am deeply concerned that MoPhone may be accessing my phone without my consent. On several occasions, I’ve noticed unusual activity such as apps opening and closing on their own, scrolling happening without my input, and my chats being accessed — all while I have no control. This is both alarming and unsettling. I would appreciate it if you could look into this matter and clarify what might be causing such occurrences.
A77: jabD2KJ | B77: jrzjkY | C77: 45769.681 | D77: recOF9e6eGRiYcPxy | E77: 10 | H77: Yes | I77: Yes | J77: No | K77: No | L77: Everything is okay but i feelclike you could.be adding someone a day before the locking of the device or a reminder for it... | M77: Yes | N77: Yes, and I am satisfied with the MoApp | O77: Phone Call – +254 728 444 442 or +254 709 924 404
A78: XxrlkNg | B78: jrzKa9 | C78: 45769.682 | D78: recvc39EvMYnkBKy9 | E78: 10 | H78: Yes | I78: Yes | J78: No | K78: No, I have never looked for customer care | L78: Na | M78: No | N78: Yes, but I am not satisfied with the MoApp | O78: Phone Call – +254 728 444 442 or +254 709 924 404 | P78: No | Q78: NA
A79: NpD5QGp | B79: 6YPqxJ | C79: 45769.683 | D79: rect5BpHLRHHJ1biS | E79: 4 | H79: Yes | I79: Yes
A80: 44BXyv5 | B80: vazlZQ | C80: 45769.683 | D80: recl5jFVrJP8eOklC | E80: 10 | H80: Yes | I80: Yes | J80: No | K80: No | L80: Very nice | M80: No | N80: Yes, and I am satisfied with the MoApp | O80: Phone Call – +254 728 444 442 or +254 709 924 404 | P80: Yes | Q80: No
A81: GxKv46o | B81: M2VWyk | C81: 45769.683 | D81: recLzhGQm212rd3Zg | E81: 4 | H81: Yes | I81: No | J81: Yes | K81: Yes | L81: I once forgot my phone lock password and you guys mkaona mnikamue proper | M81: No | N81: Yes, and I am satisfied with the MoApp | O81: Phone Call – +254 728 444 442 or +254 709 924 404 | P81: Yes | Q81: A question .........nkimaliza payment will you be still managing this handset?
A82: gDej1VN | B82: 5YVN9Q | C82: 45769.683 | D82: rec1I4Edrs4d5BdhW | E82: 10 | H82: Yes | I82: Yes | J82: No | K82: No | L82: None | M82: No | N82: No, I have never used it | O82: Phone Call – +254 728 444 442 or +254 709 924 404 | P82: No | Q82: None
A83: vGrjvjl | B83: GVbMDZ | C83: 45769.683 | D83: rec8xC0dTeg51IJAv | E83: 7 | H83: Yes | I83: Yes | J83: Yes | K83: No | L83: No challenge
A84: PdDjePV | B84: 6YPq85 | C84: 45769.683 | D84: rec3F60HEZQdHj8kA | E84: 10 | H84: Yes | I84: Yes | J84: No | K84: No | L84: It's better keep up | M84: No | N84: Yes, and I am satisfied with the MoApp | O84: MoPhones App | P84: No | Q84: It's better
A85: RGdKaAv | B85: 1yEoBL | C85: 45769.683 | D85: recvfQIzxKzdeDBFb | E85: 9 | H85: Yes | I85: Yes | J85: No | K85: Yes | L85: Online chats don't respond after hours | M85: Yes | N85: Yes, and I am satisfied with the MoApp | O85: MoPhones App | P85: No | Q85: Need fast recovery time
A86: VLjEAOE | B86: AY9kvy | C86: 45769.684 | D86: recFgufIW70gKSaF7 | E86: 0 | H86: No | I86: No | J86: Yes | K86: No | L86: I don't know if it's the phone it self because it works very slowly | M86: Yes | N86: Yes, but I am not satisfied with the MoApp | O86: MoPhones App | P86: No | Q86: I don't like the way thud phone processes it's data because it's very slow and sometimes it hangs and there a lot of space here
A87: BzK4lWY | B87: OZER5a | C87: 45769.684 | D87: rec8l8Z3r5ZlxJgYm | E87: 5 | H87: Yes | I87: Yes | J87: Yes | K87: No | L87: Payment had not reflected | M87: Yes | N87: No, I have never used it | O87: Phone Call – +254 728 444 442 or +254 709 924 404 | P87: Yes | Q87: Offer some discounts once we pay on time
A88: PdDjWjB | B88: 1YRjvp | C88: 45769.684 | D88: recQqKMpvU6GUh8jS | E88: 8 | H88: Yes | I88: Yes | J88: Yes | K88: No | L88: I was going through a financial crisis and how to improve is just to work hard | M88: No | N88: Yes, and I am satisfied with the MoApp | O88: MoPhones App | P88: No | Q88: No
A89: dWNq1BV | B89: 7zvQVZ | C89: 45769.684 | D89: reccz2gPGEAGFehDC | E89: 9 | H89: Yes | I89: Yes | J89: No | K89: No | L89: None | M89: No | N89: Yes, and I am satisfied with the MoApp | O89: Phone Call – +254 728 444 442 or +254 709 924 404 | P89: No | Q89: I am satisfied
A90: yPNZRJ0 | B90: PNr7Le | C90: 45769.684 | D90: recdvLol2P0WDO0vl | E90: 10 | H90: Yes | I90: Yes | J90: No | K90: No | L90: I have nothing to add | M90: Yes | N90: No, I have never used it | O90: MoPhones App | P90: No | Q90: Moapp is not available in apple
A91: Ek5zrl4 | B91: EG6pvN | C91: 45769.684 | D91: recVMoFHf252ywAMP | E91: 10 | H91: Yes | I91: Yes | J91: No | K91: No | L91: Nothing | M91: No | N91: Yes, and I am satisfied with the MoApp | O91: Phone Call – +254 728 444 442 or +254 709 924 404 | P91: No | Q91: I appreciate
A92: aQeNPZW | B92: ljzp9X | C92: 45769.684 | D92: rec0CsNk3ewkMBGBu | E92: 3
A93: dWNq4xq | B93: 7YEQpL | C93: 45769.685 | D93: recUXVKFRJ94o0Xtx | E93: 5 | H93: Yes | I93: Yes | J93: No | K93: Yes | L93: Being told to take photos for the second time if I want another phone yet you have my details
A94: Zjo5LXo | B94: jrzKKa | C94: 45769.685 | D94: rec9MogCjS6ixcJtm | E94: 1
A95: xXjxLay | B95: X7Qj2O | C95: 45769.686 | D95: recfGn21idkkksfKD | E95: 10 | H95: Yes | I95: Yes | J95: No | K95: No | L95: Understand in economics situation | M95: Yes | N95: Yes, but I am not satisfied with the MoApp | O95: Phone Call – +254 728 444 442 or +254 709 924 404 | P95: Yes | Q95: Poor customer service
A96: rjBybV5 | B96: OZERrA | C96: 45769.686 | D96: recrmy7WSvZjq30aU | E96: 10 | H96: Yes | I96: Yes | J96: Yes | K96: No | L96: N/A | M96: No | N96: Yes, and I am satisfied with the MoApp | O96: Free SMS – 25044 | P96: No | Q96: N/A
A97: KYeQN9M | B97: DoaQ25 | C97: 45769.687 | D97: recpY4yLXU4vvvMrB | E97: 10 | H97: Yes | I97: Yes | J97: Yes | K97: No
A98: rjBybNp | B98: 4YO5BB | C98: 45769.688 | D98: recQwlUSYREf8Oq80 | E98: 5 | H98: No | I98: Yes | J98: No | K98: No | L98: No challenge at the moment | M98: No | N98: Yes, and I am satisfied with the MoApp | O98: MoPhones App | P98: No | Q98: No
A99: q4aZ7B2 | B99: VaNrxl | C99: 45769.688 | D99: recYaOD7HcWZhQqDQ | E99: 3 | H99: No | I99: No | J99: No | K99: Yes | L99: My phone has been overheating from day 1 till now. No resolve. I have a small baby n can't make it to the offices in town. Bottleneck | M99: Yes | N99: Yes, and I am satisfied with the MoApp | O99: Reach Out via a Sales Agent | P99: No | Q99: Payment you guys are not late. Quality of phone, battery, not great. For the sum of money we pay, the phones could DEFINITELY be better
A100: Ek5zeDX | B100: W6qyYk | C100: 45769.69 | D100: recF27j93eHkcruZo | E100: 8 | H100: Yes | I100: Yes | J100: No | K100: No, I have never looked for customer care | L100: None | M100: No | N100: No, I have never used it | O100: Phone Call – +254 728 444 442 or +254 709 924 404 | P100: No | Q100: Would recommend mo phones its a 10/10
...

Sheet Duplicates
A1: Submission ID | B1: Respondent ID | C1: Submitted at | D1: Loan Id | E1: Using a scale from 0 (not likely) to 10 (very likely), how likely are you to recommend ABC Phones to friends or family? | F1: What is the main reason for your score? | G1: What is one thing we could do to improve your experience with us? | H1: Are you happy with the quality and performance of your device? | I1: Are you happy with the service and support provided by ABC Phones? | J1: Have you ever experienced a delay in your payment reflecting in your ABC account? | K1: Have you ever had difficulty getting assistance from ABC Phones customer support when needed? | L1: (If Yes) – Please describe the challenge you faced and how we can improve your experience. | M1: Have you experienced any battery-related issues with your MoPhones device? | N1: Have you used the MoPhones app (MoApp) to manage your account or make payments? | O1: Which communication channel do you prefer when contacting MoPhones for inquiries or support? | P1: Have you ever had your phone lock despite making a payment on time? | Q1: Any other Feedback?
A2: eqDZYBO | B2: AY9RGD | C2: 45769.656 | D2: recUmt3DbYL0gb025 | E2: 10 | H2: Yes | I2: Yes | J2: No | K2: No | L2: None | M2: No | N2: Yes, and I am satisfied with the MoApp | O2: Reach Out via a Sales Agent | P2: No | Q2: None
A3: aQeNaYv | B3: yRD5Dg | C3: 45769.656 | D3: recVOllpG6mFoGtaV | E3: 8 | H3: No | I3: Yes | J3: No | K3: No | L3: Battery can't store charge I need a replaced of battery | M3: Yes | N3: Yes, and I am satisfied with the MoApp | O3: Phone Call – +254 728 444 442 or +254 709 924 404 | P3: No | Q3: Kindly exchange my battery
A4: jabDkpQ | B4: gVzPBK | C4: 45769.657 | D4: recK9QseqaimraXBE | E4: 8 | H4: Yes | I4: Yes | J4: Yes | K4: No | L4: Have a 24/7 customer care services | M4: Yes | N4: Yes, but I am not satisfied with the MoApp | O4: Phone Call – +254 728 444 442 or +254 709 924 404 | P4: No | Q4: No
A5: XxrlzDL | B5: Qq4NYg | C5: 45769.66 | D5: recvDdpWZLA2VCChR | E5: 10 | H5: Yes | I5: No | J5: No | K5: Yes | L5: Support center should work 24\7 | M5: No | N5: No, I have never used it | O5: Phone Call – +254 728 444 442 or +254 709 924 404 | P5: Yes | Q5: No
A6: 2EB87Zg | B6: dozJVr | C6: 45769.662 | D6: rec4fZqbuemGwnwZF | E6: 10 | H6: Yes | I6: Yes | J6: No | K6: No | L6: No | M6: Yes | N6: No, I have never used it | O6: Phone Call – +254 728 444 442 or +254 709 924 404 | P6: No | Q6: No
A7: Y5RD9G0 | B7: Jrov97 | C7: 45769.662 | D7: recQJWCGAZ7yuy0k7 | E7: 8 | H7: Yes | I7: Yes | J7: Yes | K7: No | L7: No
A8: xXjxvbv | B8: RQjqej | C8: 45769.662 | D8: recEx6e0qdGKb242p | E8: 10 | H8: Yes | I8: Yes | J8: No | K8: No | L8: No | M8: Yes | N8: Yes, and I am satisfied with the MoApp | O8: MoPhones App | P8: No | Q8: Had some challenges at the beginning but they were sorted.The only big problem I have with device is about battery.It doesn't last even 3 hours after full charge.
A9: Ek5z6ao | B9: 6YPEOk | C9: 45769.663 | D9: recCz1heG9HYapz1Z | E9: 10 | H9: Yes | I9: Yes | J9: Yes
A10: GxKvb5p | B10: JrovLR | C10: 45769.664 | D10: recqipYF4bAylKqe7 | E10: 6 | H10: Yes | I10: Yes | J10: No | K10: No, I have never looked for customer care | L10: 0 | M10: No | N10: Yes, and I am satisfied with the MoApp | O10: MoPhones App | P10: Yes | Q10: 0
A11: J9dKoXo | B11: 2YoGkD | C11: 45769.665 | D11: recbprJ3ndI6F0BhS | E11: 7 | H11: No | I11: Yes | J11: Yes | K11: Yes | L11: Someday I texted WhatsApp | M11: Yes | N11: Yes, and I am satisfied with the MoApp | O11: Reach Out via a Sales Agent | P11: No | Q11: NA
A12: Xxrl9Yd | B12: jrzV2R | C12: 45769.671 | D12: receZqSPKKw8UDIKZ | E12: 10 | H12: Yes | I12: Yes | J12: No | K12: No | L12: No | M12: No | N12: Yes, and I am satisfied with the MoApp | O12: Phone Call – +254 728 444 442 or +254 709 924 404 | P12: No | Q12: I will definitely refer someone
A13: GNVKNZ | B13: LNYObO | C13: 45769.671 | D13: recjLCHYg0W63oFyq | E13: 9 | H13: Yes | I13: Yes | J13: No | K13: No | L13: I have never encountered any problem | M13: No | N13: No, I have never used it | O13: Reach Out via a Sales Agent | P13: No | Q13: I really appreciate the sales lady for the good work she did and helping out when i was purchasing the device 👍
A14: 68eJ9jA | B14: oZzPM1 | C14: 45769.674 | D14: recnPnRd0SWb2mvlT | E14: 10 | H14: Yes | I14: Yes | J14: No | K14: No | L14: Referred a friend but didnt get my discount | M14: No | N14: Yes, and I am satisfied with the MoApp | O14: Phone Call – +254 728 444 442 or +254 709 924 404 | P14: No | Q14: No
A15: 81zoWbz | B15: M2V4Qp | C15: 45769.675 | D15: recyRMj9xxAynZxRG | E15: 1 | H15: Yes | I15: Yes
A16: yPNZGRd | B16: AY9g0D | C16: 45769.677 | D16: recz9P2LdiWAYmkfD | E16: 9 | H16: Yes | I16: Yes | J16: No | K16: No | L16: I have not experienced any challenge but you should adjust your payments to be done daily not weekly | M16: Yes | N16: Yes, but I am not satisfied with the MoApp | O16: Phone Call – +254 728 444 442 or +254 709 924 404 | P16: Yes | Q16: I suggest daily payments
A17: 44BXdQB | B17: 5YV7Rb | C17: 45769.679 | D17: reczlWsMPQNj2ZuLG | E17: 6 | H17: Yes | I17: No | J17: Yes | K17: Yes | L17: I had an issue whereby my device battery bulged causing the screen to break and when I took it for fixing with warranty it was never replaced I now use a phone which has a cracked screen and the on screen fingerprints is no longer functional. | M17: Yes | N17: Yes, and I am satisfied with the MoApp | O17: MoPhones App | P17: No | Q17: N/A
A18: VLjEy76 | B18: 7YEyJ9 | C18: 45769.679 | D18: recgC6NF6aU6ykuWP | E18: 10 | H18: Yes | I18: Yes | J18: Yes | K18: No | L18: No | M18: No | N18: Yes, and I am satisfied with the MoApp | O18: Free SMS – 25044 | P18: Yes | Q18: None
A19: xXjxB8k | B19: 4YOMPo | C19: 45769.68 | D19: rec0ITuqc7Hbmh5I0 | E19: 9 | H19: Yes | I19: Yes | J19: Yes | K19: No | L19: So far so good | M19: No | N19: Yes, and I am satisfied with the MoApp | O19: Phone Call – +254 728 444 442 or +254 709 924 404 | P19: No | Q19: Maybe due to cureent economic times the installmwnts couod be atleast 1300 or there aboout, plus also consedaration on not locking phone before pay days, the deffier from.one customer to the other, mine is on 7th
A20: NpD5y5G | B20: NxPjab | C20: 45769.68 | D20: recNzVJ7ttBMXABMd | E20: 4 | H20: No | I20: Yes | J20: No | K20: No, I have never looked for customer care | L20: My device at times has speaker issues | M20: Yes | N20: No, I have never used it | O20: Phone Call – +254 728 444 442 or +254 709 924 404 | P20: No | Q20: How do I use warranty coz my phone has speaker issue at times
A21: VLjEALJ | B21: PNr7g1 | C21: 45769.681 | D21: reckiVrQkFIioiJEJ | E21: 10 | H21: Yes | I21: Yes | J21: No | K21: No | L21: None | M21: Yes | N21: Yes, and I am satisfied with the MoApp | O21: Phone Call – +254 728 444 442 or +254 709 924 404 | P21: No | Q21: My battery is not last for long
A22: gDej1VN | B22: 5YVN9Q | C22: 45769.683 | D22: rec1I4Edrs4d5BdhW | E22: 10 | H22: Yes | I22: Yes | J22: No | K22: No | L22: None | M22: No | N22: No, I have never used it | O22: Phone Call – +254 728 444 442 or +254 709 924 404 | P22: No | Q22: None
A23: NpD5QGp | B23: 6YPqxJ | C23: 45769.683 | D23: rect5BpHLRHHJ1biS | E23: 4 | H23: Yes | I23: Yes
A24: PdDjePV | B24: 6YPq85 | C24: 45769.683 | D24: rec3F60HEZQdHj8kA | E24: 10 | H24: Yes | I24: Yes | J24: No | K24: No | L24: It's better keep up | M24: No | N24: Yes, and I am satisfied with the MoApp | O24: MoPhones App | P24: No | Q24: It's better
A25: PdDjWjB | B25: 1YRjvp | C25: 45769.684 | D25: recQqKMpvU6GUh8jS | E25: 8 | H25: Yes | I25: Yes | J25: Yes | K25: No | L25: I was going through a financial crisis and how to improve is just to work hard | M25: No | N25: Yes, and I am satisfied with the MoApp | O25: MoPhones App | P25: No | Q25: No
A26: aQeNPZW | B26: ljzp9X | C26: 45769.684 | D26: rec0CsNk3ewkMBGBu | E26: 3
A27: BzK4lWY | B27: OZER5a | C27: 45769.684 | D27: rec8l8Z3r5ZlxJgYm | E27: 5 | H27: Yes | I27: Yes | J27: Yes | K27: No | L27: Payment had not reflected | M27: Yes | N27: No, I have never used it | O27: Phone Call – +254 728 444 442 or +254 709 924 404 | P27: Yes | Q27: Offer some discounts once we pay on time
A28: rjBybV5 | B28: OZERrA | C28: 45769.686 | D28: recrmy7WSvZjq30aU | E28: 10 | H28: Yes | I28: Yes | J28: Yes | K28: No | L28: N/A | M28: No | N28: Yes, and I am satisfied with the MoApp | O28: Free SMS – 25044 | P28: No | Q28: N/A
A29: Ek5zeDX | B29: W6qyYk | C29: 45769.69 | D29: recF27j93eHkcruZo | E29: 8 | H29: Yes | I29: Yes | J29: No | K29: No, I have never looked for customer care | L29: None | M29: No | N29: No, I have never used it | O29: Phone Call – +254 728 444 442 or +254 709 924 404 | P29: No | Q29: Would recommend mo phones its a 10/10
A30: 68eJYe5 | B30: Qq4LLX | C30: 45769.691 | D30: recKGakMTzFkL8QST | E30: 5 | H30: No
A31: pbdxXlb | B31: dozreD | C31: 45769.692 | D31: recL6XUnkmp58e4Fz | E31: 9 | H31: Yes | I31: Yes | J31: No | K31: No | L31: . | M31: No | N31: Yes, and I am satisfied with the MoApp | O31: Phone Call – +254 728 444 442 or +254 709 924 404 | P31: No | Q31: I'll recommend this to anyone at anytime Then at the bottom of my screen there is this word "device beling to your organisation " can it be deleted
A32: QKM2pvA | B32: pNza4B | C32: 45769.692 | D32: recCEq4crXYGLkUFQ | E32: 10 | H32: Yes | I32: Yes | J32: No | K32: No | L32: Na | M32: No | N32: Yes, and I am satisfied with the MoApp | O32: MoPhones App | P32: No | Q32: N/A
A33: MeDK2R8 | B33: OZEvpg | C33: 45769.692 | D33: recYbbreaZ4DitlYy | E33: 6 | H33: Yes | I33: Yes | J33: Yes | K33: Yes | L33: Yes | M33: Yes | N33: Yes, and I am satisfied with the MoApp | O33: MoPhones App | P33: Yes | Q33: Yes
A34: GxKvV1e | B34: x1Z5Py | C34: 45769.692 | D34: recis4aVIpI8lbhMO | E34: 8 | H34: Yes | I34: Yes | J34: No | K34: No | L34: No | M34: Yes | N34: Yes, and I am satisfied with the MoApp | O34: MoPhones App | P34: No | Q34: No
A35: gDejVqM | B35: 6YPoaY | C35: 45769.694 | D35: recZNI80pG0AJlJib | E35: 10 | H35: Yes | I35: Yes | J35: No | K35: No | L35: Have | M35: Yes | N35: Yes, and I am satisfied with the MoApp | O35: Phone Call – +254 728 444 442 or +254 709 924 404 | P35: No | Q35: No
A36: 81zoDgA | B36: 6YPXjJ | C36: 45769.698 | D36: recA8DuV3yLD4bP7m | E36: 7 | H36: Yes | I36: Yes | J36: No | K36: No, I have never looked for customer care | L36: Not applicable | M36: Yes | N36: Yes, and I am satisfied with the MoApp | O36: Free SMS – 25044 | P36: No | Q36: Battery drains fast
A37: 2EB8d2M | B37: yb1Wy4 | C37: 45769.699 | D37: recZixuN8JQSPpLtb | E37: 10 | H37: Yes | I37: Yes | J37: No | K37: No | L37: No | M37: No | N37: Yes, and I am satisfied with the MoApp | O37: Phone Call – +254 728 444 442 or +254 709 924 404 | P37: No | Q37: Best services
A38: xXjxov9 | B38: gVzlvD | C38: 45769.7 | D38: recwdZCb5tboLX1i6 | E38: 5 | H38: No | I38: No | J38: Yes | K38: No | L38: My phone usually hangs,the camera has started fading I don't know y....yet has not finished even half a year.... | M38: Yes | N38: Yes, and I am satisfied with the MoApp | O38: MoPhones App | P38: No | Q38: Battery drains under 10 hrs
A39: yPNZaPp | B39: AY9okD | C39: 45769.707 | D39: recYdRr5oOw861Emd | E39: 10 | H39: Yes | I39: Yes | J39: Yes | K39: No, I have never looked for customer care
A40: PdDjJVb | B40: k4zDPe | C40: 45769.707 | D40: rec9TxaSWA6t0YEV0 | E40: 0 | H40: No | I40: No | J40: No | K40: Yes | L40: No phone picking | M40: No | N40: Yes, but I am not satisfied with the MoApp | O40: Self-Service USSD – *789*25044# | P40: Yes | Q40: I'm overcharged for a phone value now is too low interest
A41: zxNX6g8 | B41: QqE2dX | C41: 45769.71 | D41: recK9eVf1vs71iEaz | E41: 10 | H41: Yes | I41: Yes | J41: No | K41: No | L41: Never experienced | M41: No | N41: Yes, and I am satisfied with the MoApp | O41: Reach Out via a Sales Agent | P41: No | Q41: Am very satisfied
A42: GxKvGxo | B42: WgXMyk | C42: 45769.714 | D42: receLhxpuuABIj8mW | E42: 10 | H42: Yes | I42: Yes | J42: No | K42: No | L42: Reflection of payment | M42: No | N42: Yes, and I am satisfied with the MoApp | O42: Phone Call – +254 728 444 442 or +254 709 924 404 | P42: No | Q42: I'm okay
A43: LZz1l4y | B43: W6Z2ZL | C43: 45769.723 | D43: recNMSZ8wZIndUOND | E43: 5 | H43: No | I43: Yes | J43: No | K43: No, I have never looked for customer care | L43: I hadn't looked for customer care yet | M43: Yes | N43: Yes, and I am satisfied with the MoApp | O43: MoPhones App | P43: Yes | Q43: The phone is usually overheating
A44: gDejKND | B44: BY9KEA | C44: 45769.724 | D44: recqOrofRZAkpigCw | E44: 5 | H44: Yes | I44: Yes | J44: No | K44: No, I have never looked for customer care | L44: No | M44: No | N44: Yes, and I am satisfied with the MoApp | O44: Phone Call – +254 728 444 442 or +254 709 924 404 | P44: No | Q44: It's a good phone
A45: J9dK7Er | B45: 7YPqP6 | C45: 45769.725 | D45: recK3ObTlGnV82mox | E45: 9 | H45: Yes | I45: Yes | J45: Yes | K45: Yes | L45: I once mistreated by one of the staff in Kimanthi streets pioneer house | M45: Yes | N45: Yes, and I am satisfied with the MoApp | O45: Phone Call – +254 728 444 442 or +254 709 924 404 | P45: No | Q45: I still can't understand how my ksh6000 shilling were used in the name of repairing the phone yet it was locked by staff of mophones
A46: VLjERQy | B46: JrBpVr | C46: 45769.731 | D46: recaMvCK6MGg1raZU | E46: 7 | H46: Yes | I46: Yes | J46: No | K46: No | L46: Battery is draining fast | M46: Yes | N46: No, I have never used it | O46: Reach Out via a Sales Agent | P46: No | Q46: Good
A47: Ek5zV92 | B47: 7YE8DA | C47: 45769.731 | D47: recAvwO3c2RyeIchE | E47: 0 | H47: No | I47: No | J47: No | K47: No | L47: Phone is overheating | M47: Yes | N47: Yes, and I am satisfied with the MoApp | O47: Phone Call – +254 728 444 442 or +254 709 924 404 | P47: No | Q47: No
A48: MeDeKzk | B48: 0YA8MZ | C48: 45769.735 | D48: reckHkeJE9yhguMIS | E48: 10 | H48: Yes | I48: Yes | J48: No | K48: No | L48: I have never had any challenge | M48: No | N48: Yes, and I am satisfied with the MoApp | O48: Phone Call – +254 728 444 442 or +254 709 924 404 | P48: No | Q48: I like the company
A49: 68e8LWo | B49: K4R1EX | C49: 45769.747 | D49: recz5yH5BhiFfXsr6 | E49: 8 | H49: Yes | I49: Yes | J49: Yes | K49: No | L49: Can you alter once am late for payment just as a reminder | M49: Yes | N49: No, I have never used it | O49: Free SMS – 25044 | P49: Yes | Q49: Have challenge with battery can't last for a day
A50: jabaZ59 | B50: X7N0bP | C50: 45769.747 | D50: recufwTagcJQrjqOX | E50: 10 | H50: Yes | I50: Yes | J50: Yes | K50: Yes | L50: Lack of 24hrs customer care services. Very frustrating. | M50: No | N50: Yes, and I am satisfied with the MoApp | O50: Reach Out via a Sales Agent | P50: Yes | Q50: You need to improve on your customer care services.
A51: ZjojEMV | B51: K4R64A | C51: 45769.755 | D51: rec7BhK2j0BW0wWiM | E51: 10 | H51: Yes | I51: Yes | J51: Yes | K51: No | L51: Open the phone immediatly after payment | M51: Yes | N51: Yes, and I am satisfied with the MoApp | O51: Phone Call – +254 728 444 442 or +254 709 924 404 | P51: No | Q51: No
A52: ODlDXvM | B52: RaL91P | C52: 45769.76 | D52: recwFJpC7Kev9Xvp8 | E52: 8 | H52: No | I52: Yes | J52: No | K52: No | L52: Never had experience with the customer service though | M52: No | N52: No, I have never used it | O52: Phone Call – +254 728 444 442 or +254 709 924 404 | P52: No | Q52: Having problem with updated apps in my device, all refused to operate says controlled by admin making my usage with the same very difficult 😕
A53: ZjojY9B | B53: rQqr4X | C53: 45769.785 | D53: recYDWYYh8zJjyMkv | H53: Yes
A54: rjBjLRl | B54: 0YAbJP | C54: 45769.789 | D54: recZAdXq7W0CSKRDt | E54: 10 | H54: Yes | I54: Yes | J54: No | K54: No | L54: Nothing | M54: No | N54: Yes, but I am not satisfied with the MoApp | O54: Phone Call – +254 728 444 442 or +254 709 924 404 | P54: No | Q54: Nothing
A55: q4a4WNg | B55: JrBV2Y | C55: 45769.789 | D55: recxKCi0IOYz2dVPE | E55: 8 | H55: Yes | I55: Yes | J55: No | K55: No | L55: None | M55: No | N55: Yes, but I am not satisfied with the MoApp | O55: Reach Out via a Sales Agent | P55: No | Q55: None
A56: QKMKk81 | B56: bMAzrg | C56: 45769.82 | D56: recNLqbyb5k87HIzv | E56: 7 | H56: Yes | I56: Yes | J56: Yes | K56: No | L56: No | M56: Yes | N56: Yes, and I am satisfied with the MoApp | O56: Phone Call – +254 728 444 442 or +254 709 924 404 | P56: No | Q56: I have an issue with commissions...when I came to you I had that there are commissions when I refer someone..now I have done 2 of them and haven't received anything...please assist
A57: GxKxMp2 | B57: 6YVEqO | C57: 45769.886 | D57: recZWWsuP4oClguJj | E57: 10 | H57: Yes | I57: Yes | J57: No | K57: No | L57: No any challenge | M57: No | N57: Yes, and I am satisfied with the MoApp | O57: Phone Call – +254 728 444 442 or +254 709 924 404 | P57: No | Q57: Thanks for good services
A58: 81z1Oy5 | B58: oZxjr1 | C58: 45769.892 | D58: recpkFVr06I6lhV3L | E58: 0 | H58: No | I58: No | K58: Yes
A59: MeD1QDk | B59: EGAJ82 | C59: 45770.065 | D59: recSJmN2tLPfGLvDl | E59: 10 | H59: Yes | I59: Yes | J59: No | K59: No | L59: No | M59: No | N59: Yes, and I am satisfied with the MoApp | O59: Reach Out via a Sales Agent | P59: No | Q59: None
A60: MeDX5Mp | B60: X79boO | C60: 45770.22 | D60: recYjydlrWhV1k8sT | E60: 10 | H60: Yes | I60: Yes | J60: No | K60: No | L60: No | M60: Yes | N60: Yes, and I am satisfied with the MoApp | O60: Phone Call – +254 728 444 442 or +254 709 924 404 | P60: No | Q60: No
A61: MeDX8ek | B61: K4ObQA | C61: 45770.252 | D61: recpnEaujfzZcAmSv | E61: 7 | H61: No | I61: Yes | J61: Yes | K61: Yes | L61: Battery | M61: Yes | N61: Yes, and I am satisfied with the MoApp | O61: Self-Service USSD – *789*25044# | P61: No | Q61: N
A62: 2EBXyjA | B62: k4pb4e | C62: 45770.305 | D62: recrQZigDi47GG0Xd | E62: 7 | H62: Yes | I62: Yes | J62: Yes | K62: Yes | L62: Payment delayed to reflect And there was once my phone hanged I needed your help but you dont | M62: Yes | N62: Yes, and I am satisfied with the MoApp | O62: Phone Call – +254 728 444 442 or +254 709 924 404 | P62: No | Q62: Am okay
A63: zxNyEa8 | B63: 9Y5q6Q | C63: 45770.56 | D63: recjo66ws3ngu5MbQ | E63: 10 | H63: Yes | I63: Yes | J63: Yes | K63: No | L63: N/a | M63: Yes | N63: Yes, and I am satisfied with the MoApp | O63: MoPhones App | P63: Yes | Q63: N/a
A64: RGd5pPQ | B64: bMXK21 | C64: 45771.539 | D64: rec4oIBuIQtVCtVwA | E64: 10 | H64: Yes | I64: Yes | J64: No | K64: No, I have never looked for customer care | L64: m | M64: Yes | N64: Yes, and I am satisfied with the MoApp | O64: Phone Call – +254 728 444 442 or +254 709 924 404 | P64: No | Q64: Make the prices better
A65: pbdGLaq | B65: a1pzNy | C65: 45772.49 | D65: recguEeHJwcx7q86Q | E65: 10 | H65: Yes | I65: Yes | J65: No | K65: No
A66: KYePKDA | B66: bMAzrg | C66: 45773.601 | D66: recNLqbyb5k87HIzv | E66: 2 | H66: No | I66: No | J66: No | K66: No | L66: Your phones are not good at all | M66: Yes | N66: Yes, and I am satisfied with the MoApp | O66: Phone Call – +254 728 444 442 or +254 709 924 404 | P66: No | Q66: I had a very big expectations on this phone Because am online driver but this phone can't work..deu to too much heating and network loss
A67: Pd1Byve | B67: Wbq2la | C67: 45783.46 | D67: recql5kphjLtb0byU | E67: 10 | H67: Yes | I67: Yes | J67: Yes | K67: No | L67: I have not faced any challenge | M67: No | N67: No, I have never used it | O67: Free SMS – 25044 | P67: Yes | Q67: I don't have any feedback
A68: q4DEqg7 | B68: j4zoBE | C68: 45783.474 | D68: recvXRQf7Lql3tZtH | E68: 4 | H68: No | I68: Yes | J68: No | K68: No | L68: 2 | M68: Yes | N68: Yes, and I am satisfied with the MoApp | O68: Phone Call – +254 728 444 442 or +254 709 924 404 | P68: Yes | Q68: None
A69: RGMBQll | B69: 60PKkB | C69: 45783.475 | D69: recy5EI2y3pUBSkda | E69: 10 | H69: Yes | I69: Yes | J69: No | K69: No | L69: N/a | M69: No | N69: Yes, and I am satisfied with the MoApp | O69: MoPhones App | P69: No | Q69: I would like to purchase another phone since the second Samsung s9 is being paid by my brother. And Samsung Galaxy A14 is used by my wife. So i need Samsung Galaxy Note 10 for myself. Kindly consider my request
A70: 9q9Jk4V | B70: 904Dap | C70: 45783.492 | D70: rect5BpHLRHHJ1biS | E70: 3 | H70: Yes | I70: Yes | J70: Yes | K70: No | L70: IMPROVE PAYMENT REFLECTION | M70: Yes | N70: No, I have never used it | O70: Free SMS – 25044 | P70: No | Q70: NONE
A71: RGMBAd4 | B71: AG8gEo | C71: 45783.494 | D71: recptyI57jqHb2BFt | E71: 9 | H71: Yes | I71: Yes | J71: No | K71: No | L71: None | M71: No | N71: No, I have never used it | O71: Reach Out via a Sales Agent | P71: No | Q71: Phone's network keep misbehaving especially when someone calls, when I'm making calls and when am about to do transactions,this is depressing
A72: obeVq1x | B72: 2doebb | C72: 45783.497 | D72: recKGakMTzFkL8QST | E72: 5 | H72: No | I72: Yes | J72: No | K72: No, I have never looked for customer care | L72: 1 | M72: Yes | N72: Yes, and I am satisfied with the MoApp | O72: Phone Call – +254 728 444 442 or +254 709 924 404 | P72: No | Q72: The camera is not clear and the battery does not hold power for long. Full battery takes about 6 hrs and it is done
A73: pbyPa6E | B73: 10Rrol | C73: 45783.503 | D73: recWpWUit7YiqlUlA | E73: 8 | H73: Yes | I73: Yes | J73: No | K73: No | L73: I haven't had any challenge | M73: No | N73: Yes, and I am satisfied with the MoApp | O73: MoPhones App | P73: No | Q73: None
A74: zxyQa9q | B74: LxO0d2 | C74: 45783.511 | D74: recvIHjYPgsEWSo3Q | E74: 10 | H74: Yes | I74: Yes | J74: No | K74: No | L74: No | M74: No | N74: Yes, and I am satisfied with the MoApp | O74: Phone Call – +254 728 444 442 or +254 709 924 404 | P74: No | Q74: Best ever
A75: VLQ9LV6 | B75: v6zLjX | C75: 45783.522 | D75: recQi0z4yg0K6Sl3H | E75: 9 | H75: Yes | I75: Yes | J75: No | K75: No | L75: Reduced number of days | M75: No | N75: Yes, and I am satisfied with the MoApp | O75: Phone Call – +254 728 444 442 or +254 709 924 404 | P75: No | Q75: Need another device but expecting at alower rate
A76: PdDjLK5 | B76: 7YEG06 | C76: 45783.528 | D76: rectpw2ZEoO1f5TkM | E76: 9 | H76: No | I76: Yes | J76: Yes | K76: No | L76: The phone is overheating even when its not in charging mode | M76: Yes | N76: Yes, but I am not satisfied with the MoApp | O76: MoPhones App | P76: Yes | Q76: Kindly contact me
A77: EkdB5G2 | B77: gPzNG1 | C77: 45783.529 | D77: reclhzp1uGJgKYNvW | E77: 10 | H77: Yes | I77: Yes | J77: No | K77: No, I have never looked for customer care | L77: Not really | M77: Yes | N77: Yes, and I am satisfied with the MoApp | O77: Phone Call – +254 728 444 442 or +254 709 924 404 | P77: No | Q77: Have said all there
A78: ja60lG6 | B78: oNzl6N | C78: 45783.54 | D78: recpkFVr06I6lhV3L | E78: 0 | H78: No | I78: No | J78: No | K78: Yes | L78: i got a phone s20 plus full of problems i can barely use it | M78: No | N78: Yes, and I am satisfied with the MoApp | O78: Phone Call – +254 728 444 442 or +254 709 924 404 | P78: Yes | Q78: no
A79: 9q9659E | B79: r9YQ9o | C79: 45783.597 | D79: recnskub8CcSkcnrt | E79: 8 | H79: Yes | I79: Yes | J79: No | K79: No | L79: No challenges | M79: Yes | N79: Yes, and I am satisfied with the MoApp | O79: MoPhones App | P79: No | Q79: None
A80: ja60R61 | B80: pqzQMq | C80: 45783.622 | D80: recozbH0rJvgQlpGZ | E80: 8 | H80: Yes | I80: Yes | J80: No | K80: No | L80: None | M80: Yes | N80: Yes, and I am satisfied with the MoApp | O80: Phone Call – +254 728 444 442 or +254 709 924 404 | P80: No | Q80: None
A81: 9q968z5 | B81: 8Dr9XA | C81: 45783.627 | D81: recopw807ijyfYSt5 | E81: 6 | H81: Yes | I81: Yes | J81: Yes | K81: No | L81: When using another phone | M81: Yes | N81: Yes, and I am satisfied with the MoApp | O81: MoPhones App | P81: Yes | Q81: Nop
A82: dWaZrKN | B82: pqzagq | C82: 45783.635 | D82: rec9HXLrt6sdHbGIF | E82: 10 | H82: Yes | I82: Yes | J82: Yes | K82: No | L82: Because your services fevers every one | M82: Yes | N82: No, I have never used it | O82: Phone Call – +254 728 444 442 or +254 709 924 404 | P82: Yes | Q82: The battery doesn't hold power for long
A83: eqDZv1O | B83: G4LKLk | C83: 45784.134 | D83: rec0HrmbKcHdVBS0N | E83: 3 | H83: Yes | I83: Yes | J83: No | K83: No | L83: Non | M83: No | N83: Yes, and I am satisfied with the MoApp | O83: Phone Call – +254 728 444 442 or +254 709 924 404 | P83: Yes | Q83: No
A84: Pd1B72d | B84: l1LK9o | C84: 45784.708 | D84: rec5pgfzE9sNbW6MI | E84: 9 | H84: Yes | I84: Yes | J84: No | K84: No | L84: They have responded positively when i needed them | M84: Yes | N84: Yes, and I am satisfied with the MoApp | O84: Phone Call – +254 728 444 442 or +254 709 924 404 | P84: No | Q84: Would suggest that there be a fkexible payment method let's say a daily payment method that allows you to use the phone when only you can afford the daily charges
... A86: A72oevk | B86: 60PKkB | C86: 45788.581 | D86: recy5EI2y3pUBSkda | E86: 10 | H86: Yes | I86: Yes | J86: No | K86: No | L86: You are the best in service production | M86: No | N86: Yes, and I am satisfied with the MoApp | O86: MoPhones App | P86: No | Q86: Your phones are the best
A87: lbOk5gX | B87: BJ2ZOQ | C87: 45795.324 | D87: recBd7NAjVdtmYbIW | E87: 6
A88: MeapgpM | B88: eGzXYe | C88: 45795.327 | D88: recRWTGs5DWMaJVUb | E88: 10 | H88: Yes | I88: Yes | J88: No | K88: No | L88: No | M88: Yes | N88: Yes, and I am satisfied with the MoApp | O88: MoPhones App | P88: No | Q88: The phone has a bad battery
A89: 68KE9kP | B89: PZGlQP | C89: 45795.328 | D89: recgxIBSCAxDSZ5bT | E89: 5 | H89: No | I89: Yes | J89: No | K89: No | L89: No | M89: Yes | N89: Yes, and I am satisfied with the MoApp | O89: Phone Call – +254 728 444 442 or +254 709 924 404 | P89: Yes | Q89: Personally the Only problem Am facing with my my device is bringing it back to you for repair now and then. I have been in your office pioneer house for more than 6 times The screen is dimming off on its own. I have paid my device three quarter, I have now given up on this Samsung note 20. My ID 30127155
A90: 5B9P57Z | B90: JEWDyz | C90: 45795.333 | D90: reclV957PJowsgrCF | E90: 8 | H90: Yes | I90: Yes | J90: No | K90: No | L90: Ok | M90: No | N90: Yes, and I am satisfied with the MoApp | O90: MoPhones App | P90: No | Q90: No
A91: 2EB8oNg | B91: rQYMBp | C91: 45795.333 | D91: recY1T7InO4NGs4I2 | E91: 10 | H91: Yes | I91: Yes | J91: Yes | K91: Yes | L91: You need to put one contact | M91: No | N91: Yes, and I am satisfied with the MoApp | O91: Free SMS – 25044 | P91: No | Q91: No
A92: 2EAG5ML | B92: RqVYXK | C92: 45795.336 | D92: recri36SyjFAYah5u | E92: 10 | H92: Yes | I92: Yes | J92: No | K92: No, I have never looked for customer care | L92: i think everything is well | M92: Yes | N92: No, I have never used it | O92: Free SMS – 25044 | P92: No | Q92: i dont have anything else
A93: 2EAGyve | B93: L46Jd1 | C93: 45795.337 | D93: reckAeNgVLfxBZq0S | E93: 10 | H93: Yes | I93: Yes | J93: No | K93: No | L93: Am okay | M93: Yes | N93: Yes, and I am satisfied with the MoApp | O93: Self-Service USSD – *789*25044# | P93: Yes | Q93: Just okay
A94: b5eQy6L | B94: x8lPPJ | C94: 45795.338 | D94: recEojr7uurePlbjZ | E94: 10 | H94: Yes | I94: Yes | J94: No | K94: No | L94: None | M94: Yes | N94: Yes, and I am satisfied with the MoApp | O94: Free SMS – 25044 | P94: No | Q94: None for now
A95: LZz1qvz | B95: PNroWx | C95: 45795.367 | D95: recMbq0BKT2x5kP4T | E95: 10 | H95: Yes | I95: Yes | J95: No | K95: No | L95: Everything is well | M95: No | N95: Yes, and I am satisfied with the MoApp | O95: MoPhones App | P95: Yes | Q95: Good service
A96: vGD58rv | B96: 0qDozZ | C96: 45795.372 | D96: recW8LK1T4RtzlgGC | E96: 9 | H96: Yes | I96: Yes | J96: Yes | K96: Yes | L96: Bot response,never responds | M96: No | N96: No, I have never used it | O96: Reach Out via a Sales Agent | P96: No | Q96: Inprove on bot response
A97: XxoP6Ze | B97: RqVvLp | C97: 45795.378 | D97: recyqGx7s1EwojCCj | E97: 1 | H97: Yes | I97: Yes | J97: Yes | K97: Yes | L97: Mostly delay in receiving calls when calling | M97: Yes | N97: Yes, and I am satisfied with the MoApp | O97: Phone Call – +254 728 444 442 or +254 709 924 404 | P97: Yes | Q97: Battery runs out quickly
A98: 7Rblr19 | B98: RaLygv | C98: 45795.393 | D98: recPG0DYTJYTqGMDD | E98: 4 | H98: No | I98: Yes | J98: No | K98: Yes | L98: About my 5g networking | M98: Yes | N98: Yes, and I am satisfied with the MoApp | O98: MoPhones App | P98: Yes | Q98: I need help
A99: jaoARQY | B99: j8kkD6 | C99: 45795.395 | D99: recVDddS8uVoK9uQD | E99: 6 | H99: Yes | I99: Yes | J99: Yes | K99: No | L99: N/A | M99: No | N99: Yes, and I am satisfied with the MoApp | O99: Phone Call – +254 728 444 442 or +254 709 924 404 | P99: No | Q99: make it easy for people to access the app after locking, sometimes fails and uiu want to make payment
... A103: LZK2R4j | B103: 8bMk5A | C103: 45795.638 | D103: recTa8o3gQkTm3lP4 | E103: 8 | H103: Yes | I103: Yes | J103: No | K103: Yes | L103: Network problem | M103: No | N103: Yes, and I am satisfied with the MoApp | O103: Self-Service USSD – *789*25044# | P103: No | Q103: Nòooo
A104: 447MDab | B104: dJzv5V | C104: 45796.1 | D104: recWRnWE25sYXEhah | E104: 7 | H104: No | I104: Yes | J104: No | K104: Yes | L104: The offices are different and I couldn't be assuming they are | M104: No
...
